[{ "_id" : { "$oid" : "5344d4cc57d8c9771f7d0932" }, "city" : "Phoenix", "neighborhood" : "Alhambra", "review_count" : 3, "name" : "Tony's Pizzeria", "checkin" : { "checkin_info" : { "0-5" : 1, "15-1" : 1, "15-4" : 1, "22-2" : 1, "17-1" : 1, "14-2" : 1 }, "_id" : { "$oid" : "5344d6d957d8c9771f7e5eba" }, "type" : "checkin", "business_id" : "M0UqoJlAUzKx6dW2CT8d8w" }, "full_address" : "7804 N 27th Ave\nPhoenix, AZ 85051", "hours" : { "Tuesday" : { "close" : "23:00", "open" : "11:00" }, "Friday" : { "close" : "02:00", "open" : "11:00" }, "Wednesday" : { "close" : "23:00", "open" : "11:00" }, "Thursday" : { "close" : "23:00", "open" : "11:00" }, "Sunday" : { "close" : "23:00", "open" : "17:00" }, "Saturday" : { "close" : "02:00", "open" : "11:00" } }, "state" : "AZ", "longitude" : -112.1169946, "stars" : 4, "latitude" : 33.5513424, "attributes" : { "Take-out" : true, "Price Range" : 1, "Alcohol" : "none", "Noise Level" : "average", "Attire" : "casual", "Delivery" : true, "Has TV" : true, "Outdoor Seating" : false, "Parking" : { "garage" : false, "street" : false, "validated" : false, "lot" : true, "valet" : false }, "Ambience" : { "romantic" : false, "intimate" : false, "touristy" : false, "hipster" : false, "divey" : false, "classy" : false, "trendy" : false, "upscale" : false, "casual" : false }, "Accepts Credit Cards" : true, "Good for Kids" : true, "Good For Groups" : true, "Wheelchair Accessible" : true }, "categories" : [ "Pizza", "Restaurants" ], "votes" : [ { "funny" : 0, "useful" : 2, "cool" : 1 }, { "funny" : 0, "useful" : 0, "cool" : 2 }, { "funny" : 0, "useful" : 0, "cool" : 0 } ], "open" : false },{ "_id" : { "$oid" : "5344d4cc57d8c9771f7d0958" }, "city" : "Phoenix", "neighborhood" : "Sinaloa Plaza", "review_count" : 8, "name" : "Tortas Paquime", "checkin" : { "checkin_info" : { "11-2" : 2, "15-0" : 3, "15-3" : 1, "15-5" : 1, "18-0" : 1, "18-3" : 1, "18-4" : 2, "18-6" : 1, "14-4" : 1, "14-0" : 1, "14-1" : 1, "14-2" : 2, "14-3" : 1, "13-3" : 2, "13-6" : 1, "11-3" : 1, "13-4" : 1, "12-5" : 1, "12-3" : 2, "12-0" : 1, "12-1" : 1, "20-4" : 1, "16-2" : 1, "16-0" : 1, "16-1" : 1, "10-1" : 1, "10-4" : 1 }, "_id" : { "$oid" : "5344d6d957d8c9771f7e5e0c" }, "type" : "checkin", "business_id" : "YD0oiqWZyAi-lMw3TQ2TqA" }, "full_address" : "3024 W Van Buren St\nSte 146\nPhoenix, AZ 85009", "hours" : { "Monday" : { "close" : "22:00", "open" : "08:00" }, "Tuesday" : { "close" : "22:00", "open" : "08:00" }, "Friday" : { "close" : "22:00", "open" : "08:00" }, "Wednesday" : { "close" : "22:00", "open" : "08:00" }, "Thursday" : { "close" : "22:00", "open" : "08:00" }, "Sunday" : { "close" : "22:00", "open" : "08:00" }, "Saturday" : { "close" : "22:00", "open" : "08:00" } }, "state" : "AZ", "longitude" : -112.1247145, "stars" : 4.5, "latitude" : 33.4515612, "attributes" : { "Take-out" : true, "Accepts Credit Cards" : true, "Price Range" : 1, "Outdoor Seating" : true, "Caters" : true, "Parking" : { "garage" : false, "street" : false, "validated" : false, "lot" : false, "valet" : false }, "Attire" : "casual", "Has TV" : true, "Good For" : { "dessert" : false, "latenight" : false, "lunch" : true, "dinner" : false, "breakfast" : false, "brunch" : false }, "Takes Reservations" : false, "Ambience" : { "romantic" : false, "intimate" : false, "touristy" : false, "hipster" : false, "divey" : false, "classy" : false, "trendy" : false, "upscale" : false, "casual" : false }, "Waiter Service" : false, "Wi-Fi" : "no", "Good for Kids" : true, "Good For Groups" : true, "Alcohol" : "none" }, "categories" : [ "Mexican", "Restaurants" ], "votes" : [ { "funny" : 0, "useful" : 0, "cool" : 0 }, { "funny" : 0, "useful" : 0, "cool" : 0 }, { "funny" : 1, "useful" : 3, "cool" : 4 }, { "funny" : 2, "useful" : 2, "cool" : 1 }, { "funny" : 3, "useful" : 5, "cool" : 4 } ], "open" : true },{ "_id" : { "$oid" : "5344d4cc57d8c9771f7d0966" }, "city" : "Phoenix", "neighborhood" : "North Mountain", "review_count" : 6, "name" : "El Pollo Loco", "checkin" : { "checkin_info" : { "15-4" : 1, "15-6" : 1, "18-1" : 1, "18-2" : 1, "18-5" : 1, "18-6" : 1, "14-5" : 1, "14-3" : 1, "19-4" : 1, "19-0" : 2, "19-3" : 1, "13-3" : 2, "11-4" : 2, "13-0" : 1, "11-1" : 2, "11-0" : 2, "21-5" : 2, "12-5" : 1, "12-2" : 3, "12-1" : 2, "20-5" : 1, "20-4" : 1, "16-3" : 1, "17-3" : 1, "17-1" : 1, "17-0" : 1, "10-1" : 2, "10-3" : 1, "10-4" : 1, "21-1" : 1 }, "_id" : { "$oid" : "5344d6db57d8c9771f7e82e6" }, "type" : "checkin", "business_id" : "YaB2hKgWUaqAWnCA6YWD7g" }, "full_address" : "2410 W Northern Ave\nPhoenix, AZ 85021", "hours" : { "Monday" : { "close" : "23:00", "open" : "09:00" }, "Tuesday" : { "close" : "23:00", "open" : "09:00" }, "Friday" : { "close" : "23:00", "open" : "09:00" }, "Wednesday" : { "close" : "23:00", "open" : "09:00" }, "Thursday" : { "close" : "23:00", "open" : "09:00" }, "Sunday" : { "close" : "23:00", "open" : "09:00" }, "Saturday" : { "close" : "23:00", "open" : "09:00" } }, "state" : "AZ", "longitude" : -112.110289, "stars" : 3.5, "latitude" : 33.553485, "attributes" : { "Alcohol" : "none", "Attire" : "casual", "Good For" : { "dessert" : false, "latenight" : false, "lunch" : false, "dinner" : false, "breakfast" : false, "brunch" : false }, "Delivery" : false, "Outdoor Seating" : false, "Parking" : { "garage" : false, "street" : false, "validated" : false, "lot" : false, "valet" : false }, "Accepts Credit Cards" : true, "Good for Kids" : true, "Price Range" : 1 }, "categories" : [ "Fast Food", "Mexican", "Restaurants" ], "votes" : [ { "funny" : 0, "useful" : 0, "cool" : 0 }, { "funny" : 0, "useful" : 2, "cool" : 0 }, { "funny" : 0, "useful" : 0, "cool" : 0 }, { "funny" : 2, "useful" : 1, "cool" : 1 }, { "funny" : 0, "useful" : 1, "cool" : 1 } ], "open" : true },{ "_id" : { "$oid" : "5344d4cc57d8c9771f7d0905" }, "city" : "Phoenix", "neighborhood" : "Ahwatukee", "review_count" : 40, "name" : "Macayo's Mexican Kitchen", "checkin" : { "checkin_info" : { "11-2" : 3, "16-5" : 4, "17-4" : 6, "15-1" : 3, "15-0" : 2, "15-3" : 1, "15-2" : 1, "17-5" : 8, "15-6" : 2, "18-0" : 1, "18-1" : 6, "18-2" : 3, "18-3" : 2, "18-4" : 6, "18-5" : 6, "18-6" : 4, "14-4" : 2, "14-5" : 3, "14-6" : 3, "14-2" : 2, "14-3" : 1, "0-5" : 1, "10-0" : 2, "19-5" : 4, "19-4" : 5, "19-6" : 3, "19-1" : 1, "19-0" : 2, "19-3" : 2, "19-2" : 3, "11-5" : 4, "13-2" : 3, "13-0" : 2, "11-1" : 1, "11-0" : 1, "13-5" : 3, "13-4" : 1, "12-6" : 4, "12-4" : 3, "12-5" : 2, "12-2" : 6, "12-3" : 4, "12-0" : 1, "12-1" : 2, "13-3" : 1, "11-6" : 2, "11-4" : 2, "20-1" : 2, "20-0" : 1, "20-3" : 1, "20-2" : 2, "20-5" : 3, "16-2" : 2, "16-3" : 2, "16-0" : 1, "16-1" : 2, "16-6" : 2, "17-2" : 3, "17-1" : 2, "17-0" : 1, "21-4" : 2, "17-3" : 3, "10-2" : 1, "10-3" : 1, "10-4" : 1, "21-3" : 2 }, "_id" : { "$oid" : "5344d6db57d8c9771f7e7efc" }, "type" : "checkin", "business_id" : "aACW1qAdOfgcU8yX61dOFw" }, "full_address" : "12637 S 48th St\nPhoenix, AZ 85044", "hours" : { "Monday" : { "close" : "22:00", "open" : "11:00" }, "Tuesday" : { "close" : "22:00", "open" : "11:00" }, "Friday" : { "close" : "23:00", "open" : "11:00" }, "Wednesday" : { "close" : "22:00", "open" : "11:00" }, "Thursday" : { "close" : "22:00", "open" : "11:00" }, "Sunday" : { "close" : "22:00", "open" : "11:00" }, "Saturday" : { "close" : "23:00", "open" : "11:00" } }, "state" : "AZ", "longitude" : -111.980062, "stars" : 3, "latitude" : 33.331946, "attributes" : { "Take-out" : true, "Price Range" : 2, "Outdoor Seating" : true, "Caters" : true, "Noise Level" : "average", "Parking" : { "garage" : false, "street" : false, "validated" : false, "lot" : true, "valet" : false }, "Good For Groups" : true, "Delivery" : false, "Attire" : "casual", "Has TV" : true, "Good For" : { "dessert" : false, "latenight" : false, "lunch" : true, "dinner" : true, "breakfast" : false, "brunch" : false }, "Takes Reservations" : true, "Ambience" : { "romantic" : false, "intimate" : false, "touristy" : false, "hipster" : false, "divey" : false, "classy" : false, "trendy" : false, "upscale" : false, "casual" : false }, "Waiter Service" : true, "Accepts Credit Cards" : true, "Good for Kids" : true, "Alcohol" : "full_bar", "Wheelchair Accessible" : true }, "categories" : [ "Mexican", "Restaurants" ], "votes" : [ { "funny" : 1, "useful" : 3, "cool" : 1 }, { "funny" : 0, "useful" : 0, "cool" : 0 }, { "funny" : 1, "useful" : 2, "cool" : 1 }, { "funny" : 0, "useful" : 1, "cool" : 0 }, { "funny" : 0, "useful" : 2, "cool" : 0 }, { "funny" : 0, "useful" : 0, "cool" : 0 }, { "funny" : 0, "useful" : 0, "cool" : 0 }, { "funny" : 0, "useful" : 1, "cool" : 0 }, { "funny" : 2, "useful" : 2, "cool" : 1 }, { "funny" : 2, "useful" : 4, "cool" : 2 }, { "funny" : 2, "useful" : 0, "cool" : 0 }, { "funny" : 1, "useful" : 2, "cool" : 0 }, { "funny" : 0, "useful" : 0, "cool" : 0 }, { "funny" : 0, "useful" : 1, "cool" : 1 }, { "funny" : 0, "useful" : 0, "cool" : 0 }, { "funny" : 0, "useful" : 0, "cool" : 0 }, { "funny" : 0, "useful" : 0, "cool" : 0 }, { "funny" : 0, "useful" : 4, "cool" : 2 }, { "funny" : 2, "useful" : 2, "cool" : 2 }, { "funny" : 1, "useful" : 1, "cool" : 1 }, { "funny" : 1, "useful" : 2, "cool" : 1 }, { "funny" : 1, "useful" : 5, "cool" : 2 }, { "funny" : 1, "useful" : 1, "cool" : 0 }, { "funny" : 0, "useful" : 0, "cool" : 0 }, { "funny" : 1, "useful" : 2, "cool" : 1 }, { "funny" : 0, "useful" : 0, "cool" : 0 }, { "funny" : 1, "useful" : 1, "cool" : 0 }, { "funny" : 0, "useful" : 1, "cool" : 2 }, { "funny" : 0, "useful" : 2, "cool" : 0 }, { "funny" : 1, "useful" : 3, "cool" : 1 }, { "funny" : 0, "useful" : 0, "cool" : 0 }, { "funny" : 0, "useful" : 0, "cool" : 1 }, { "funny" : 2, "useful" : 8, "cool" : 4 }, { "funny" : 0, "useful" : 1, "cool" : 0 }, { "funny" : 1, "useful" : 3, "cool" : 1 }, { "funny" : 2, "useful" : 3, "cool" : 2 }, { "funny" : 2, "useful" : 5, "cool" : 3 }, { "funny" : 2, "useful" : 1, "cool" : 0 } ], "open" : true },{ "_id" : { "$oid" : "5344d4cc57d8c9771f7d0915" }, "city" : "Phoenix", "neighborhood" : "Ahwatukee Foothills", "review_count" : 50, "name" : "Ezekiel's Restaurant", "checkin" : { "checkin_info" : { "15-3" : 1, "15-5" : 2, "15-4" : 1, "18-2" : 1, "18-3" : 2, "18-4" : 3, "18-5" : 2, "14-0" : 1, "17-5" : 1, "14-3" : 1, "17-1" : 2, "19-4" : 4, "16-5" : 4, "19-0" : 1, "19-3" : 1, "19-2" : 2, "13-3" : 2, "13-2" : 1, "13-1" : 1, "13-0" : 2, "11-1" : 1, "11-0" : 2, "13-5" : 1, "11-2" : 2, "12-4" : 1, "12-5" : 3, "12-3" : 1, "12-0" : 4, "12-1" : 2, "11-5" : 2, "20-1" : 1, "20-4" : 2, "16-0" : 1, "17-4" : 4, "17-3" : 1, "16-4" : 1, "17-0" : 2, "10-0" : 2, "10-1" : 2, "10-2" : 1, "10-4" : 1, "13-6" : 1 }, "_id" : { "$oid" : "5344d6db57d8c9771f7e8237" }, "type" : "checkin", "business_id" : "SGGZ6l345YTww09IHxtoew" }, "full_address" : "4825 E Warner Rd\nPhoenix, AZ 85044", "hours" : { "Monday" : { "close" : "20:00", "open" : "11:00" }, "Tuesday" : { "close" : "20:00", "open" : "11:00" }, "Friday" : { "close" : "20:00", "open" : "11:00" }, "Wednesday" : { "close" : "20:00", "open" : "11:00" }, "Thursday" : { "close" : "20:00", "open" : "11:00" }, "Sunday" : { "close" : "17:00", "open" : "12:00" }, "Saturday" : { "close" : "20:00", "open" : "11:00" } }, "state" : "AZ", "longitude" : -111.979372836649, "stars" : 4, "latitude" : 33.3293584260744, "attributes" : { "Take-out" : true, "Accepts Credit Cards" : true, "Price Range" : 2, "Outdoor Seating" : true, "Caters" : true, "Noise Level" : "average", "Parking" : { "garage" : false, "street" : false, "validated" : false, "lot" : true, "valet" : false }, "Good For Groups" : true, "Delivery" : true, "Attire" : "casual", "Has TV" : false, "Good For" : { "dessert" : false, "latenight" : false, "lunch" : true, "dinner" : true, "breakfast" : false, "brunch" : false }, "Takes Reservations" : false, "Ambience" : { "romantic" : false, "intimate" : false, "touristy" : false, "hipster" : false, "divey" : false, "classy" : false, "trendy" : false, "upscale" : false, "casual" : true }, "Waiter Service" : false, "Wi-Fi" : "no", "Good for Kids" : true, "Alcohol" : "none", "Wheelchair Accessible" : true }, "categories" : [ "Food", "Soul Food", "American (New)", "Desserts", "Restaurants" ], "votes" : [ { "funny" : 0, "useful" : 0, "cool" : 0 }, { "funny" : 0, "useful" : 0, "cool" : 0 }, { "funny" : 0, "useful" : 0, "cool" : 0 }, { "funny" : 1, "useful" : 1, "cool" : 0 }, { "funny" : 0, "useful" : 2, "cool" : 1 }, { "funny" : 0, "useful" : 0, "cool" : 0 }, { "funny" : 0, "useful" : 0, "cool" : 0 }, { "funny" : 0, "useful" : 1, "cool" : 0 }, { "funny" : 0, "useful" : 0, "cool" : 0 }, { "funny" : 0, "useful" : 2, "cool" : 2 }, { "funny" : 3, "useful" : 1, "cool" : 0 }, { "funny" : 0, "useful" : 0, "cool" : 0 }, { "funny" : 0, "useful" : 4, "cool" : 2 }, { "funny" : 2, "useful" : 4, "cool" : 1 }, { "funny" : 0, "useful" : 2, "cool" : 0 }, { "funny" : 0, "useful" : 0, "cool" : 0 }, { "funny" : 0, "useful" : 0, "cool" : 0 }, { "funny" : 0, "useful" : 0, "cool" : 0 }, { "funny" : 0, "useful" : 0, "cool" : 0 }, { "funny" : 0, "useful" : 0, "cool" : 0 }, { "funny" : 0, "useful" : 5, "cool" : 0 }, { "funny" : 0, "useful" : 2, "cool" : 0 }, { "funny" : 0, "useful" : 0, "cool" : 0 }, { "funny" : 0, "useful" : 0, "cool" : 0 }, { "funny" : 1, "useful" : 3, "cool" : 0 }, { "funny" : 2, "useful" : 4, "cool" : 0 }, { "funny" : 1, "useful" : 2, "cool" : 0 }, { "funny" : 0, "useful" : 0, "cool" : 0 }, { "funny" : 0, "useful" : 0, "cool" : 0 }, { "funny" : 0, "useful" : 0, "cool" : 0 }, { "funny" : 0, "useful" : 1, "cool" : 0 }, { "funny" : 0, "useful" : 0, "cool" : 0 }, { "funny" : 0, "useful" : 0, "cool" : 0 }, { "funny" : 1, "useful" : 0, "cool" : 0 }, { "funny" : 0, "useful" : 0, "cool" : 1 }, { "funny" : 0, "useful" : 0, "cool" : 0 }, { "funny" : 0, "useful" : 2, "cool" : 1 }, { "funny" : 0, "useful" : 0, "cool" : 0 }, { "funny" : 1, "useful" : 1, "cool" : 1 }, { "funny" : 0, "useful" : 0, "cool" : 0 }, { "funny" : 0, "useful" : 2, "cool" : 0 }, { "funny" : 0, "useful" : 2, "cool" : 2 }, { "funny" : 0, "useful" : 0, "cool" : 0 }, { "funny" : 0, "useful" : 2, "cool" : 0 }, { "funny" : 0, "useful" : 0, "cool" : 0 } ], "open" : true },{ "_id" : { "$oid" : "5344d4cc57d8c9771f7d0926" }, "city" : "Phoenix", "neighborhood" : "Desert Ridge", "review_count" : 42, "name" : "Smashburger", "checkin" : { "checkin_info" : { "11-2" : 2, "21-4" : 2, "10-6" : 1, "15-1" : 2, "17-4" : 2, "15-2" : 1, "17-5" : 2, "15-6" : 1, "18-0" : 3, "18-1" : 4, "18-2" : 3, "18-3" : 1, "18-4" : 1, "18-5" : 3, "18-6" : 3, "14-5" : 5, "14-6" : 2, "19-5" : 1, "19-4" : 2, "19-6" : 2, "19-1" : 3, "19-0" : 2, "19-3" : 1, "11-5" : 4, "11-4" : 3, "13-0" : 1, "13-6" : 2, "13-5" : 3, "13-4" : 3, "12-6" : 7, "12-4" : 3, "12-5" : 5, "12-2" : 2, "12-3" : 7, "12-0" : 5, "12-1" : 3, "13-3" : 2, "11-6" : 3, "13-2" : 1, "20-3" : 1, "20-2" : 1, "20-4" : 2, "16-0" : 1, "16-1" : 1, "17-2" : 2, "17-1" : 2, "17-0" : 2, "10-0" : 1, "10-1" : 1, "21-2" : 1, "21-3" : 1 }, "_id" : { "$oid" : "5344d6da57d8c9771f7e76a0" }, "type" : "checkin", "business_id" : "qAORECtABjr_FsvSzy1apw" }, "full_address" : "21001 N  Tatum Blvd\nSte 34-1140\nPhoenix, AZ 85050", "hours" : { "Monday" : { "close" : "22:00", "open" : "10:00" }, "Tuesday" : { "close" : "22:00", "open" : "10:00" }, "Friday" : { "close" : "22:00", "open" : "10:00" }, "Wednesday" : { "close" : "22:00", "open" : "10:00" }, "Thursday" : { "close" : "22:00", "open" : "10:00" }, "Sunday" : { "close" : "22:00", "open" : "10:00" }, "Saturday" : { "close" : "22:00", "open" : "10:00" } }, "state" : "AZ", "longitude" : -111.969461, "stars" : 3.5, "latitude" : 33.678131, "attributes" : { "Take-out" : true, "Accepts Credit Cards" : true, "Drive-Thru" : false, "Outdoor Seating" : true, "Caters" : false, "Noise Level" : "average", "Parking" : { "garage" : false, "street" : false, "validated" : false, "lot" : true, "valet" : false }, "Delivery" : false, "Attire" : "casual", "Has TV" : false, "Price Range" : 2, "Good For" : { "dessert" : false, "latenight" : false, "lunch" : true, "dinner" : false, "breakfast" : false, "brunch" : false }, "Takes Reservations" : false, "Ambience" : { "romantic" : false, "intimate" : false, "touristy" : false, "hipster" : false, "divey" : false, "classy" : false, "trendy" : false, "upscale" : false, "casual" : true }, "Waiter Service" : false, "Wi-Fi" : "free", "Good for Kids" : true, "Good For Groups" : true, "Alcohol" : "none" }, "categories" : [ "Burgers", "American (Traditional)", "Hot Dogs", "Restaurants" ], "votes" : [ { "funny" : 0, "useful" : 0, "cool" : 0 }, { "funny" : 0, "useful" : 0, "cool" : 0 }, { "funny" : 0, "useful" : 0, "cool" : 0 }, { "funny" : 0, "useful" : 0, "cool" : 0 }, { "funny" : 0, "useful" : 2, "cool" : 1 }, { "funny" : 0, "useful" : 1, "cool" : 0 }, { "funny" : 0, "useful" : 0, "cool" : 0 }, { "funny" : 0, "useful" : 0, "cool" : 0 }, { "funny" : 0, "useful" : 0, "cool" : 0 }, { "funny" : 0, "useful" : 1, "cool" : 1 }, { "funny" : 0, "useful" : 1, "cool" : 0 }, { "funny" : 0, "useful" : 0, "cool" : 0 }, { "funny" : 0, "useful" : 0, "cool" : 0 }, { "funny" : 0, "useful" : 0, "cool" : 0 }, { "funny" : 0, "useful" : 0, "cool" : 1 }, { "funny" : 0, "useful" : 2, "cool" : 1 }, { "funny" : 2, "useful" : 5, "cool" : 4 }, { "funny" : 0, "useful" : 3, "cool" : 1 }, { "funny" : 0, "useful" : 1, "cool" : 1 }, { "funny" : 0, "useful" : 1, "cool" : 0 }, { "funny" : 0, "useful" : 0, "cool" : 0 }, { "funny" : 0, "useful" : 0, "cool" : 0 }, { "funny" : 6, "useful" : 6, "cool" : 5 }, { "funny" : 0, "useful" : 2, "cool" : 0 }, { "funny" : 0, "useful" : 0, "cool" : 0 }, { "funny" : 0, "useful" : 0, "cool" : 0 }, { "funny" : 0, "useful" : 0, "cool" : 0 }, { "funny" : 0, "useful" : 0, "cool" : 0 }, { "funny" : 0, "useful" : 0, "cool" : 0 }, { "funny" : 1, "useful" : 0, "cool" : 0 }, { "funny" : 0, "useful" : 1, "cool" : 0 }, { "funny" : 0, "useful" : 1, "cool" : 1 }, { "funny" : 0, "useful" : 0, "cool" : 0 }, { "funny" : 0, "useful" : 0, "cool" : 0 }, { "funny" : 0, "useful" : 0, "cool" : 0 }, { "funny" : 1, "useful" : 0, "cool" : 0 }, { "funny" : 0, "useful" : 2, "cool" : 1 } ], "open" : true },{ "_id" : { "$oid" : "5344d4cc57d8c9771f7d0a10" }, "city" : "Phoenix", "neighborhood" : "North Mountain", "review_count" : 16, "name" : "Port of Subs", "checkin" : { "checkin_info" : { "11-2" : 7, "18-0" : 1, "18-1" : 2, "14-4" : 1, "14-1" : 1, "14-2" : 1, "16-4" : 1, "9-0" : 4, "19-6" : 1, "13-3" : 1, "11-4" : 4, "13-1" : 2, "11-1" : 8, "13-6" : 2, "11-3" : 7, "13-4" : 1, "12-6" : 1, "12-4" : 4, "12-2" : 3, "12-3" : 3, "12-0" : 7, "12-1" : 5, "9-1" : 5, "11-5" : 2, "9-3" : 5, "9-2" : 6, "9-4" : 2, "17-3" : 1, "17-1" : 1, "10-0" : 8, "10-1" : 8, "10-2" : 9, "10-3" : 8, "10-4" : 4, "10-5" : 1, "11-0" : 6 }, "_id" : { "$oid" : "5344d6da57d8c9771f7e754d" }, "type" : "checkin", "business_id" : "-aDuOZelvBHWKh-NrXooow" }, "full_address" : "2737 W Thunderbird Rd\nPhoenix, AZ 85053", "hours" : { "Monday" : { "close" : "21:00", "open" : "09:00" }, "Tuesday" : { "close" : "21:00", "open" : "09:00" }, "Friday" : { "close" : "21:00", "open" : "09:00" }, "Wednesday" : { "close" : "21:00", "open" : "09:00" }, "Thursday" : { "close" : "21:00", "open" : "09:00" }, "Sunday" : { "close" : "20:00", "open" : "09:00" }, "Saturday" : { "close" : "20:00", "open" : "09:00" } }, "state" : "AZ", "longitude" : -112.119194, "stars" : 3.5, "latitude" : 33.609811, "attributes" : { "Take-out" : true, "Accepts Credit Cards" : true, "Price Range" : 1, "Outdoor Seating" : true, "Caters" : true, "Noise Level" : "average", "Parking" : { "garage" : false, "street" : false, "validated" : false, "lot" : true, "valet" : false }, "Good For Groups" : true, "Delivery" : false, "Dogs Allowed" : false, "Attire" : "casual", "Has TV" : false, "Good For" : { "dessert" : false, "latenight" : false, "lunch" : true, "dinner" : true, "breakfast" : false, "brunch" : false }, "Takes Reservations" : false, "Ambience" : { "romantic" : false, "intimate" : false, "touristy" : false, "hipster" : false, "divey" : false, "classy" : false, "trendy" : false, "upscale" : false, "casual" : true }, "Waiter Service" : false, "Wi-Fi" : "free", "Good for Kids" : true, "Alcohol" : "none", "Wheelchair Accessible" : true }, "categories" : [ "Sandwiches", "Restaurants" ], "votes" : [ { "funny" : 0, "useful" : 0, "cool" : 0 }, { "funny" : 0, "useful" : 0, "cool" : 0 }, { "funny" : 1, "useful" : 1, "cool" : 1 }, { "funny" : 0, "useful" : 1, "cool" : 0 }, { "funny" : 0, "useful" : 1, "cool" : 0 }, { "funny" : 0, "useful" : 3, "cool" : 2 }, { "funny" : 0, "useful" : 1, "cool" : 0 }, { "funny" : 0, "useful" : 0, "cool" : 0 }, { "funny" : 0, "useful" : 1, "cool" : 1 }, { "funny" : 2, "useful" : 4, "cool" : 3 }, { "funny" : 0, "useful" : 0, "cool" : 0 }, { "funny" : 0, "useful" : 0, "cool" : 0 }, { "funny" : 0, "useful" : 0, "cool" : 0 }, { "funny" : 0, "useful" : 0, "cool" : 0 }, { "funny" : 1, "useful" : 1, "cool" : 0 } ], "open" : true },{ "_id" : { "$oid" : "5344d4cc57d8c9771f7d0a5d" }, "city" : "Phoenix", "neighborhood" : "Thomas Centre", "review_count" : 7, "name" : "Palermos Pizza", "checkin" : { "checkin_info" : { "18-3" : 2, "15-6" : 1, "17-4" : 1, "16-6" : 2, "13-5" : 1, "11-1" : 1, "10-4" : 1 }, "_id" : { "$oid" : "5344d6da57d8c9771f7e74d0" }, "type" : "checkin", "business_id" : "hVDo35_OySCeFWYLFKM7WQ" }, "full_address" : "9024 W Thomas Rd\nPhoenix, AZ 85037", "hours" : { "Monday" : { "close" : "22:30", "open" : "10:30" }, "Tuesday" : { "close" : "22:30", "open" : "10:30" }, "Friday" : { "close" : "23:30", "open" : "10:30" }, "Wednesday" : { "close" : "22:30", "open" : "10:30" }, "Thursday" : { "close" : "22:30", "open" : "10:30" }, "Sunday" : { "close" : "22:30", "open" : "11:30" }, "Saturday" : { "close" : "23:30", "open" : "10:30" } }, "state" : "AZ", "longitude" : -112.2536443, "stars" : 3.5, "latitude" : 33.4797253, "attributes" : { "Take-out" : true, "Accepts Credit Cards" : true, "Price Range" : 2, "Outdoor Seating" : false, "Caters" : false, "Noise Level" : "average", "Parking" : { "garage" : false, "street" : false, "validated" : false, "lot" : false, "valet" : false }, "Good For Groups" : true, "Delivery" : true, "Attire" : "casual", "Has TV" : true, "Good For" : { "dessert" : false, "latenight" : false, "lunch" : false, "dinner" : false, "breakfast" : false, "brunch" : false }, "Takes Reservations" : false, "Ambience" : { "romantic" : false, "intimate" : false, "touristy" : false, "hipster" : false, "divey" : false, "classy" : false, "trendy" : false, "upscale" : false, "casual" : false }, "Waiter Service" : false, "Wi-Fi" : "no", "Good for Kids" : true, "Alcohol" : "beer_and_wine", "Wheelchair Accessible" : true }, "categories" : [ "Italian", "Pizza", "Restaurants" ], "votes" : [ { "funny" : 0, "useful" : 2, "cool" : 0 }, { "funny" : 0, "useful" : 0, "cool" : 0 }, { "funny" : 0, "useful" : 0, "cool" : 0 }, { "funny" : 1, "useful" : 2, "cool" : 1 }, { "funny" : 0, "useful" : 1, "cool" : 0 }, { "funny" : 0, "useful" : 0, "cool" : 0 } ], "open" : true },{ "_id" : { "$oid" : "5344d4cc57d8c9771f7d0be2" }, "city" : "Phoenix", "neighborhood" : "Desert Ridge", "review_count" : 35, "name" : "Islands Restaurant", "checkin" : { "checkin_info" : { "17-0" : 4, "13-5" : 3, "22-3" : 1, "10-6" : 2, "17-6" : 1, "15-1" : 1, "15-0" : 1, "15-3" : 2, "15-2" : 2, "15-5" : 3, "16-0" : 3, "15-6" : 2, "18-0" : 1, "18-1" : 4, "18-2" : 4, "18-3" : 6, "18-4" : 10, "18-5" : 10, "18-6" : 2, "21-5" : 2, "14-4" : 2, "14-5" : 1, "14-6" : 4, "14-0" : 1, "21-6" : 2, "17-1" : 8, "19-5" : 3, "19-4" : 9, "19-6" : 2, "19-1" : 6, "19-3" : 2, "19-2" : 1, "11-5" : 5, "11-4" : 5, "13-0" : 1, "11-1" : 2, "11-0" : 5, "11-3" : 2, "11-2" : 4, "12-6" : 7, "12-4" : 5, "12-5" : 6, "12-2" : 2, "12-3" : 3, "12-0" : 2, "12-1" : 1, "11-6" : 4, "13-2" : 1, "20-0" : 7, "20-3" : 1, "20-5" : 5, "20-4" : 2, "20-6" : 1, "16-2" : 2, "16-3" : 2, "17-5" : 9, "17-4" : 5, "16-6" : 2, "17-2" : 1, "16-4" : 3, "16-5" : 2, "17-3" : 3, "10-2" : 1, "10-3" : 1, "10-4" : 1, "10-5" : 1, "21-2" : 1, "13-6" : 2 }, "_id" : { "$oid" : "5344d6da57d8c9771f7e6f6c" }, "type" : "checkin", "business_id" : "e0vubCKi8KD8zC2C6FdbuQ" }, "full_address" : "21001 N Tatum Blvd\nSte 36-1160\nPhoenix, AZ 85050", "hours" : { "Monday" : { "close" : "21:30", "open" : "11:00" }, "Tuesday" : { "close" : "21:30", "open" : "11:00" }, "Friday" : { "close" : "22:30", "open" : "11:00" }, "Wednesday" : { "close" : "21:30", "open" : "11:00" }, "Thursday" : { "close" : "21:30", "open" : "11:00" }, "Sunday" : { "close" : "21:30", "open" : "11:00" }, "Saturday" : { "close" : "22:30", "open" : "11:00" } }, "state" : "AZ", "longitude" : -111.9746066, "stars" : 3.5, "latitude" : 33.678615, "attributes" : { "Drive-Thru" : false, "Alcohol" : "full_bar", "Noise Level" : "average", "Has TV" : true, "Attire" : "casual", "Ambience" : { "romantic" : false, "intimate" : false, "touristy" : false, "hipster" : false, "divey" : false, "classy" : false, "trendy" : false, "upscale" : false, "casual" : true }, "Good for Kids" : true, "Price Range" : 2, "Good For Dancing" : false, "Delivery" : false, "Coat Check" : false, "Accepts Credit Cards" : true, "Take-out" : true, "Wheelchair Accessible" : true, "Outdoor Seating" : true, "Takes Reservations" : false, "Waiter Service" : true, "Wi-Fi" : "no", "Caters" : true, "Good For" : { "dessert" : false, "latenight" : false, "lunch" : true, "dinner" : true, "breakfast" : false, "brunch" : false }, "Parking" : { "garage" : false, "street" : false, "validated" : false, "lot" : true, "valet" : false }, "Music" : { "dj" : false, "background_music" : true, "jukebox" : false, "live" : false, "video" : false, "karaoke" : false }, "Good For Groups" : true }, "categories" : [ "Bars", "American (Traditional)", "Burgers", "Nightlife", "Sports Bars", "Restaurants" ], "votes" : [ { "funny" : 0, "useful" : 0, "cool" : 0 }, { "funny" : 0, "useful" : 0, "cool" : 0 }, { "funny" : 0, "useful" : 0, "cool" : 0 }, { "funny" : 0, "useful" : 0, "cool" : 0 }, { "funny" : 1, "useful" : 2, "cool" : 2 }, { "funny" : 1, "useful" : 0, "cool" : 0 }, { "funny" : 0, "useful" : 0, "cool" : 0 }, { "funny" : 0, "useful" : 0, "cool" : 0 }, { "funny" : 0, "useful" : 0, "cool" : 0 }, { "funny" : 0, "useful" : 0, "cool" : 0 }, { "funny" : 0, "useful" : 0, "cool" : 0 }, { "funny" : 0, "useful" : 0, "cool" : 0 }, { "funny" : 0, "useful" : 0, "cool" : 0 }, { "funny" : 0, "useful" : 0, "cool" : 0 }, { "funny" : 0, "useful" : 0, "cool" : 0 }, { "funny" : 0, "useful" : 1, "cool" : 0 }, { "funny" : 0, "useful" : 0, "cool" : 0 }, { "funny" : 0, "useful" : 1, "cool" : 0 }, { "funny" : 0, "useful" : 2, "cool" : 0 }, { "funny" : 0, "useful" : 2, "cool" : 0 }, { "funny" : 1, "useful" : 2, "cool" : 2 }, { "funny" : 1, "useful" : 4, "cool" : 1 }, { "funny" : 1, "useful" : 0, "cool" : 0 }, { "funny" : 0, "useful" : 0, "cool" : 0 }, { "funny" : 0, "useful" : 1, "cool" : 0 }, { "funny" : 0, "useful" : 0, "cool" : 0 }, { "funny" : 0, "useful" : 0, "cool" : 0 }, { "funny" : 0, "useful" : 1, "cool" : 1 }, { "funny" : 5, "useful" : 5, "cool" : 4 }, { "funny" : 0, "useful" : 0, "cool" : 0 }, { "funny" : 0, "useful" : 0, "cool" : 0 }, { "funny" : 0, "useful" : 1, "cool" : 0 } ], "open" : true },{ "_id" : { "$oid" : "5344d4cc57d8c9771f7d0bff" }, "city" : "Phoenix", "neighborhood" : "South Mountain", "review_count" : 8, "name" : "Susie's Mexican Cafe & Lounge", "checkin" : { "checkin_info" : { "11-2" : 2, "11-3" : 1, "13-4" : 1, "10-0" : 1, "10-3" : 3, "14-3" : 1 }, "_id" : { "$oid" : "5344d6d957d8c9771f7e6699" }, "type" : "checkin", "business_id" : "-d1I0dwtCg1IIjnI3DZ38Q" }, "full_address" : "4044 S 16th St\nPhoenix, AZ 85040", "hours" : { "Monday" : { "close" : "22:00", "open" : "09:00" }, "Tuesday" : { "close" : "22:00", "open" : "09:00" }, "Friday" : { "close" : "22:00", "open" : "09:00" }, "Wednesday" : { "close" : "22:00", "open" : "09:00" }, "Thursday" : { "close" : "22:00", "open" : "09:00" }, "Sunday" : { "close" : "22:00", "open" : "09:00" }, "Saturday" : { "close" : "22:00", "open" : "09:00" } }, "state" : "AZ", "longitude" : -112.0471014, "stars" : 3.5, "latitude" : 33.4088426, "attributes" : { "Take-out" : true, "Price Range" : 1, "Outdoor Seating" : true, "Noise Level" : "quiet", "Parking" : { "garage" : false, "street" : false, "validated" : false, "lot" : true, "valet" : false }, "Delivery" : false, "Attire" : "casual", "Has TV" : true, "Good For" : { "dessert" : false, "latenight" : false, "lunch" : true, "dinner" : false, "breakfast" : false, "brunch" : false }, "Takes Reservations" : false, "Ambience" : { "romantic" : false, "intimate" : false, "touristy" : false, "hipster" : false, "divey" : false, "classy" : false, "trendy" : false, "upscale" : false, "casual" : false }, "Waiter Service" : true, "Accepts Credit Cards" : true, "Good for Kids" : true, "Good For Groups" : true, "Alcohol" : "full_bar" }, "categories" : [ "Mexican", "Restaurants" ], "votes" : [ { "funny" : 2, "useful" : 2, "cool" : 2 }, { "funny" : 2, "useful" : 2, "cool" : 2 }, { "funny" : 0, "useful" : 0, "cool" : 0 }, { "funny" : 0, "useful" : 0, "cool" : 0 }, { "funny" : 0, "useful" : 1, "cool" : 0 }, { "funny" : 10, "useful" : 16, "cool" : 13 }, { "funny" : 0, "useful" : 0, "cool" : 0 }, { "funny" : 4, "useful" : 4, "cool" : 3 } ], "open" : true },{ "_id" : { "$oid" : "5344d4cc57d8c9771f7d0c3a" }, "city" : "Phoenix", "neighborhood" : "Camelback East", "review_count" : 11, "name" : "Phoenix House Of Pizza And Subs", "checkin" : { "checkin_info" : { "8-1" : 1, "11-4" : 1, "9-6" : 1, "12-3" : 1, "13-3" : 1, "13-2" : 1, "11-1" : 1, "11-0" : 2, "18-6" : 1, "11-2" : 3, "12-4" : 1, "12-2" : 1, "14-1" : 2, "12-0" : 1, "12-1" : 3 }, "_id" : { "$oid" : "5344d6d857d8c9771f7e5ab8" }, "type" : "checkin", "business_id" : "ZAgPh4v-oOb1g6cdlkKI0g" }, "full_address" : "326 N 48th St\nPhoenix, AZ 85008", "hours" : { "Monday" : { "close" : "16:00", "open" : "10:00" }, "Tuesday" : { "close" : "16:00", "open" : "10:00" }, "Friday" : { "close" : "16:00", "open" : "10:00" }, "Wednesday" : { "close" : "16:00", "open" : "10:00" }, "Thursday" : { "close" : "16:00", "open" : "10:00" }, "Saturday" : { "close" : "18:00", "open" : "10:00" } }, "state" : "AZ", "longitude" : -111.9786425, "stars" : 3.5, "latitude" : 33.4520972, "attributes" : { "Take-out" : true, "Price Range" : 1, "Outdoor Seating" : false, "Noise Level" : "average", "Parking" : { "garage" : false, "street" : true, "validated" : false, "lot" : true, "valet" : false }, "Good For Groups" : true, "Delivery" : false, "Attire" : "casual", "Has TV" : true, "Good For" : { "dessert" : false, "latenight" : false, "lunch" : true, "dinner" : false, "breakfast" : false, "brunch" : false }, "Takes Reservations" : true, "Ambience" : { "romantic" : false, "intimate" : false, "touristy" : false, "hipster" : false, "divey" : false, "classy" : false, "trendy" : false, "upscale" : false, "casual" : false }, "Waiter Service" : false, "Accepts Credit Cards" : true, "Good for Kids" : true, "Alcohol" : "none", "Wheelchair Accessible" : true }, "categories" : [ "Italian", "Pizza", "Sandwiches", "Restaurants" ], "votes" : [ { "funny" : 9, "useful" : 10, "cool" : 6 }, { "funny" : 0, "useful" : 1, "cool" : 1 }, { "funny" : 0, "useful" : 0, "cool" : 0 }, { "funny" : 1, "useful" : 4, "cool" : 3 }, { "funny" : 0, "useful" : 1, "cool" : 0 }, { "funny" : 0, "useful" : 0, "cool" : 0 }, { "funny" : 3, "useful" : 2, "cool" : 2 }, { "funny" : 9, "useful" : 3, "cool" : 5 }, { "funny" : 0, "useful" : 1, "cool" : 0 } ], "open" : true },{ "_id" : { "$oid" : "5344d4cc57d8c9771f7d0d6f" }, "city" : "Phoenix", "neighborhood" : "Paradise Valley", "review_count" : 10, "name" : "Firehouse Subs", "checkin" : { "checkin_info" : { "18-0" : 1, "11-6" : 1, "19-4" : 2, "15-2" : 1, "19-1" : 1, "11-5" : 1, "18-3" : 1, "11-1" : 1, "12-6" : 1, "12-5" : 1, "10-4" : 1, "10-5" : 2, "10-6" : 1 }, "_id" : { "$oid" : "5344d6db57d8c9771f7e81ee" }, "type" : "checkin", "business_id" : "iKXnctUJOVxenM42ERcekg" }, "full_address" : "15530 N Tatum Blvd\nSte 130\nPhoenix, AZ 85032", "hours" : { "Monday" : { "close" : "22:00", "open" : "10:00" }, "Tuesday" : { "close" : "22:00", "open" : "10:00" }, "Friday" : { "close" : "22:00", "open" : "10:00" }, "Wednesday" : { "close" : "22:00", "open" : "10:00" }, "Thursday" : { "close" : "22:00", "open" : "10:00" }, "Sunday" : { "close" : "22:00", "open" : "10:00" }, "Saturday" : { "close" : "22:00", "open" : "10:00" } }, "state" : "AZ", "longitude" : -111.9779084, "stars" : 3.5, "latitude" : 33.6278262, "attributes" : { "Take-out" : true, "Drive-Thru" : false, "Noise Level" : "average", "Attire" : "casual", "Delivery" : false, "Has TV" : true, "Outdoor Seating" : true, "Takes Reservations" : false, "Ambience" : { "romantic" : false, "intimate" : false, "classy" : false, "hipster" : false, "divey" : false, "touristy" : false, "trendy" : false, "upscale" : false, "casual" : false }, "Accepts Credit Cards" : true, "Price Range" : 2 }, "categories" : [ "Delis", "Fast Food", "Sandwiches", "Restaurants" ], "votes" : [ { "funny" : 0, "useful" : 0, "cool" : 0 }, { "funny" : 0, "useful" : 0, "cool" : 0 }, { "funny" : 0, "useful" : 1, "cool" : 0 }, { "funny" : 0, "useful" : 1, "cool" : 0 }, { "funny" : 0, "useful" : 0, "cool" : 0 }, { "funny" : 0, "useful" : 0, "cool" : 0 }, { "funny" : 0, "useful" : 0, "cool" : 1 }, { "funny" : 0, "useful" : 0, "cool" : 0 }, { "funny" : 0, "useful" : 0, "cool" : 0 } ], "open" : true },{ "_id" : { "$oid" : "5344d4cc57d8c9771f7d0e18" }, "city" : "Phoenix", "neighborhood" : "Maryvale", "review_count" : 4, "name" : "Coco's Family Restaurant", "checkin" : { "checkin_info" : { "11-1" : 1, "19-4" : 1, "19-3" : 1, "20-6" : 1, "13-3" : 1, "18-1" : 1, "18-2" : 1, "18-4" : 1, "11-0" : 2, "10-1" : 1, "10-0" : 1, "16-6" : 1, "12-4" : 1, "10-6" : 1, "18-5" : 1 }, "_id" : { "$oid" : "5344d6da57d8c9771f7e6cff" }, "type" : "checkin", "business_id" : "K-FzqJUj6YpSLC_fyJRnlA" }, "full_address" : "2612 N 75th Ave\nPhoenix, AZ 85035", "hours" : { "Monday" : { "close" : "21:00", "open" : "06:00" }, "Tuesday" : { "close" : "21:00", "open" : "06:00" }, "Friday" : { "close" : "21:00", "open" : "06:00" }, "Wednesday" : { "close" : "21:00", "open" : "06:00" }, "Thursday" : { "close" : "21:00", "open" : "06:00" }, "Sunday" : { "close" : "21:00", "open" : "06:00" }, "Saturday" : { "close" : "21:00", "open" : "06:00" } }, "state" : "AZ", "longitude" : -112.2210838, "stars" : 4, "latitude" : 33.4768658, "attributes" : { "Take-out" : true, "Accepts Credit Cards" : true, "Price Range" : 2, "Outdoor Seating" : false, "Caters" : false, "Noise Level" : "quiet", "Parking" : { "garage" : false, "street" : false, "validated" : false, "lot" : false, "valet" : false }, "Delivery" : false, "Attire" : "casual", "Has TV" : false, "Good For" : { "dessert" : false, "latenight" : false, "lunch" : false, "dinner" : false, "breakfast" : false, "brunch" : false }, "Takes Reservations" : false, "Ambience" : { "romantic" : false, "intimate" : false, "touristy" : false, "hipster" : false, "divey" : false, "classy" : false, "trendy" : false, "upscale" : false, "casual" : true }, "Waiter Service" : true, "Wi-Fi" : "free", "Good for Kids" : true, "Good For Groups" : true, "Alcohol" : "beer_and_wine" }, "categories" : [ "Bakeries", "Food", "American (Traditional)", "Sandwiches", "Restaurants" ], "votes" : [ { "funny" : 0, "useful" : 0, "cool" : 0 }, { "funny" : 0, "useful" : 0, "cool" : 0 }, { "funny" : 2, "useful" : 3, "cool" : 3 }, { "funny" : 0, "useful" : 1, "cool" : 1 } ], "open" : true },{ "_id" : { "$oid" : "5344d4cc57d8c9771f7d0e27" }, "city" : "Phoenix", "neighborhood" : "Paradise Valley", "review_count" : 11, "name" : "La Tortotota", "checkin" : { "checkin_info" : { "11-6" : 1, "20-2" : 1, "17-6" : 1, "19-5" : 1, "15-5" : 1, "7-0" : 1, "19-1" : 2, "13-1" : 1, "13-3" : 1, "13-2" : 1, "16-0" : 1, "18-3" : 2, "22-3" : 1, "18-5" : 3, "13-5" : 1, "12-5" : 1, "12-1" : 1 }, "_id" : { "$oid" : "5344d6da57d8c9771f7e74f1" }, "type" : "checkin", "business_id" : "grk9RANQRR-IZouPFP3kgA" }, "full_address" : "16816 N Cave Creek  Rd\nPhoenix, AZ 85022", "hours" : { "Monday" : { "close" : "21:00", "open" : "11:00" }, "Tuesday" : { "close" : "21:00", "open" : "11:00" }, "Friday" : { "close" : "22:00", "open" : "11:00" }, "Wednesday" : { "close" : "21:00", "open" : "11:00" }, "Thursday" : { "close" : "21:00", "open" : "11:00" }, "Sunday" : { "close" : "21:00", "open" : "11:00" }, "Saturday" : { "close" : "22:00", "open" : "11:00" } }, "state" : "AZ", "longitude" : -112.0308641, "stars" : 3.5, "latitude" : 33.6391172, "attributes" : { "Take-out" : true, "Accepts Credit Cards" : true, "Outdoor Seating" : false, "Caters" : false, "Noise Level" : "average", "Parking" : { "garage" : false, "street" : false, "validated" : false, "lot" : false, "valet" : false }, "Delivery" : false, "Ambience" : { "romantic" : false, "intimate" : false, "touristy" : false, "hipster" : false, "divey" : false, "classy" : false, "trendy" : false, "upscale" : false, "casual" : false }, "Has TV" : true, "Good For" : { "dessert" : false, "latenight" : false, "lunch" : true, "dinner" : false, "breakfast" : false, "brunch" : false }, "Takes Reservations" : false, "Attire" : "casual", "Waiter Service" : true, "Wi-Fi" : "no", "Good for Kids" : true, "Good For Groups" : true, "Price Range" : 1 }, "categories" : [ "Mexican", "Restaurants" ], "votes" : [ { "funny" : 1, "useful" : 0, "cool" : 0 }, { "funny" : 3, "useful" : 6, "cool" : 2 }, { "funny" : 0, "useful" : 1, "cool" : 0 }, { "funny" : 1, "useful" : 0, "cool" : 0 }, { "funny" : 2, "useful" : 1, "cool" : 0 }, { "funny" : 0, "useful" : 1, "cool" : 0 }, { "funny" : 1, "useful" : 0, "cool" : 0 }, { "funny" : 1, "useful" : 4, "cool" : 0 }, { "funny" : 1, "useful" : 1, "cool" : 0 }, { "funny" : 0, "useful" : 1, "cool" : 0 } ], "open" : true },{ "_id" : { "$oid" : "5344d4cc57d8c9771f7d0ead" }, "city" : "Phoenix", "neighborhood" : "Paradise Valley", "review_count" : 14, "name" : "Humberto's Mexican Food", "checkin" : { "checkin_info" : { "9-0" : 1, "22-6" : 1, "17-3" : 1, "11-0" : 1, "12-6" : 1, "22-3" : 1 }, "_id" : { "$oid" : "5344d6da57d8c9771f7e7cb5" }, "type" : "checkin", "business_id" : "CHCm6hbR4KSstbifFdCOpw" }, "full_address" : "3607 E Bell Rd\nPhoenix, AZ 85032", "hours" : { "Monday" : { "close" : "22:00", "open" : "07:00" }, "Tuesday" : { "close" : "22:00", "open" : "07:00" }, "Friday" : { "close" : "22:00", "open" : "07:00" }, "Wednesday" : { "close" : "22:00", "open" : "07:00" }, "Thursday" : { "close" : "22:00", "open" : "07:00" }, "Sunday" : { "close" : "22:00", "open" : "07:00" }, "Saturday" : { "close" : "22:00", "open" : "07:00" } }, "state" : "AZ", "longitude" : -112.004291, "stars" : 3.5, "latitude" : 33.640076, "attributes" : { "Take-out" : true, "Accepts Credit Cards" : true, "Price Range" : 1, "Outdoor Seating" : false, "Noise Level" : "quiet", "Parking" : { "garage" : false, "street" : true, "validated" : false, "lot" : false, "valet" : false }, "Good For Groups" : true, "Delivery" : false, "Good For" : { "dessert" : false, "latenight" : false, "lunch" : false, "dinner" : true, "breakfast" : false, "brunch" : false }, "Takes Reservations" : false, "Attire" : "casual", "Waiter Service" : false, "Wi-Fi" : "no", "Good for Kids" : true, "Alcohol" : "none", "Wheelchair Accessible" : true }, "categories" : [ "Mexican", "Restaurants" ], "votes" : [ { "funny" : 0, "useful" : 2, "cool" : 1 }, { "funny" : 0, "useful" : 0, "cool" : 0 }, { "funny" : 0, "useful" : 1, "cool" : 0 }, { "funny" : 1, "useful" : 2, "cool" : 0 }, { "funny" : 1, "useful" : 4, "cool" : 0 }, { "funny" : 0, "useful" : 0, "cool" : 0 }, { "funny" : 1, "useful" : 2, "cool" : 0 }, { "funny" : 0, "useful" : 1, "cool" : 0 }, { "funny" : 0, "useful" : 1, "cool" : 0 }, { "funny" : 0, "useful" : 0, "cool" : 0 }, { "funny" : 0, "useful" : 1, "cool" : 0 }, { "funny" : 0, "useful" : 0, "cool" : 0 } ], "open" : false },{ "_id" : { "$oid" : "5344d4cc57d8c9771f7d0edd" }, "city" : "Phoenix", "neighborhood" : "Paradise Gateway", "review_count" : 5, "name" : "Paradise Bakery & Cafe", "checkin" : { "checkin_info" : { "15-5" : 1, "18-2" : 1, "17-4" : 1, "18-5" : 1, "16-6" : 1, "14-1" : 1, "14-2" : 1, "14-3" : 1, "16-5" : 1, "13-3" : 1, "13-2" : 1, "11-6" : 2, "11-1" : 1, "12-6" : 2, "12-3" : 1, "11-4" : 1, "10-4" : 1, "17-5" : 1, "13-0" : 1, "17-3" : 1, "17-2" : 1, "17-0" : 1, "10-0" : 1, "10-1" : 1, "10-2" : 2, "8-0" : 2, "10-5" : 1 }, "_id" : { "$oid" : "5344d6d957d8c9771f7e5f46" }, "type" : "checkin", "business_id" : "Wf_5BXVcvHRgFkbPtx5nhw" }, "full_address" : "10625 N Tatum Blvd\nPhoenix, AZ 85028", "hours" : { "Monday" : { "close" : "21:00", "open" : "06:00" }, "Tuesday" : { "close" : "21:00", "open" : "06:00" }, "Friday" : { "close" : "21:00", "open" : "06:00" }, "Wednesday" : { "close" : "21:00", "open" : "06:00" }, "Thursday" : { "close" : "21:00", "open" : "06:00" }, "Sunday" : { "close" : "18:00", "open" : "06:00" }, "Saturday" : { "close" : "21:00", "open" : "06:00" } }, "state" : "AZ", "longitude" : -111.9770187, "stars" : 2, "latitude" : 33.5834449, "attributes" : { "Take-out" : true, "Accepts Credit Cards" : true, "Price Range" : 2, "Outdoor Seating" : true, "Noise Level" : "average", "Parking" : { "garage" : false, "street" : false, "validated" : false, "lot" : false, "valet" : false }, "Delivery" : false, "Attire" : "casual", "Good For" : { "dessert" : false, "latenight" : false, "lunch" : false, "dinner" : false, "breakfast" : false, "brunch" : false }, "Takes Reservations" : false, "Ambience" : { "romantic" : false, "intimate" : false, "touristy" : false, "hipster" : false, "divey" : false, "classy" : false, "trendy" : false, "upscale" : false, "casual" : false }, "Waiter Service" : false, "Wi-Fi" : "free", "Good for Kids" : true, "Good For Groups" : false, "Alcohol" : "none" }, "categories" : [ "Cafes", "Sandwiches", "Restaurants" ], "votes" : [ { "funny" : 1, "useful" : 2, "cool" : 1 }, { "funny" : 0, "useful" : 0, "cool" : 0 }, { "funny" : 0, "useful" : 1, "cool" : 0 }, { "funny" : 0, "useful" : 1, "cool" : 0 } ], "open" : true },{ "_id" : { "$oid" : "5344d4cc57d8c9771f7d1044" }, "city" : "Phoenix", "neighborhood" : "North Mountain", "review_count" : 8, "name" : "Boston Market", "checkin" : { "checkin_info" : { "15-1" : 1, "15-4" : 1, "18-1" : 2, "18-3" : 1, "18-5" : 1, "14-4" : 1, "14-5" : 1, "14-1" : 1, "14-3" : 1, "19-4" : 1, "19-2" : 2, "11-5" : 1, "13-2" : 2, "13-1" : 1, "11-6" : 2, "11-1" : 2, "11-0" : 1, "11-3" : 1, "13-4" : 1, "12-6" : 1, "12-2" : 2, "12-3" : 1, "12-1" : 2, "20-3" : 1, "17-5" : 1, "16-6" : 1, "16-4" : 2, "17-0" : 1, "21-5" : 1, "10-4" : 1, "21-1" : 1 }, "_id" : { "$oid" : "5344d6d957d8c9771f7e6278" }, "type" : "checkin", "business_id" : "PSAK5sUss8yiN7Q_72Zlxw" }, "full_address" : "8001 N 19th Ave\nPhoenix, AZ 85021", "hours" : { "Monday" : { "close" : "21:30", "open" : "11:00" }, "Tuesday" : { "close" : "21:30", "open" : "11:00" }, "Friday" : { "close" : "21:30", "open" : "11:00" }, "Wednesday" : { "close" : "21:30", "open" : "11:00" }, "Thursday" : { "close" : "21:30", "open" : "11:00" }, "Sunday" : { "close" : "21:30", "open" : "11:00" }, "Saturday" : { "close" : "21:30", "open" : "11:00" } }, "state" : "AZ", "longitude" : -112.099212, "stars" : 3.5, "latitude" : 33.553471, "attributes" : { "Take-out" : true, "Price Range" : 2, "Outdoor Seating" : false, "Caters" : true, "Takes Reservations" : false, "Good For Groups" : true, "Delivery" : false, "Good For" : { "dessert" : false, "latenight" : false, "lunch" : false, "dinner" : false, "breakfast" : false, "brunch" : false }, "Parking" : { "garage" : false, "street" : false, "validated" : false, "lot" : false, "valet" : false }, "Attire" : "casual", "Waiter Service" : false, "Accepts Credit Cards" : true, "Good for Kids" : true, "Alcohol" : "none", "Wheelchair Accessible" : true }, "categories" : [ "American (Traditional)", "Comfort Food", "Barbeque", "Restaurants" ], "votes" : [ { "funny" : 0, "useful" : 1, "cool" : 0 }, { "funny" : 0, "useful" : 0, "cool" : 0 }, { "funny" : 1, "useful" : 2, "cool" : 2 }, { "funny" : 1, "useful" : 2, "cool" : 1 }, { "funny" : 2, "useful" : 3, "cool" : 2 }, { "funny" : 0, "useful" : 0, "cool" : 0 }, { "funny" : 0, "useful" : 1, "cool" : 1 } ], "open" : true },{ "_id" : { "$oid" : "5344d4cc57d8c9771f7d104b" }, "city" : "Phoenix", "neighborhood" : "North Gateway", "review_count" : 40, "name" : "Connolly's Sports Grill", "checkin" : { "checkin_info" : { "22-5" : 3, "22-4" : 3, "22-3" : 1, "22-2" : 2, "22-1" : 1, "22-0" : 6, "19-5" : 6, "19-4" : 6, "19-6" : 5, "19-1" : 4, "19-0" : 3, "19-3" : 3, "19-2" : 6, "11-5" : 4, "11-6" : 3, "11-0" : 1, "11-3" : 2, "11-2" : 2, "12-6" : 3, "12-5" : 1, "16-2" : 4, "16-3" : 9, "16-0" : 9, "16-1" : 12, "16-6" : 2, "16-4" : 7, "16-5" : 4, "21-4" : 4, "21-5" : 5, "21-6" : 1, "21-0" : 6, "21-1" : 3, "21-2" : 3, "21-3" : 2, "15-1" : 3, "15-0" : 2, "15-3" : 4, "15-2" : 3, "15-5" : 4, "15-4" : 6, "15-6" : 2, "18-0" : 3, "18-1" : 3, "18-2" : 6, "18-3" : 4, "18-4" : 5, "18-5" : 10, "18-6" : 3, "8-5" : 2, "8-3" : 1, "23-3" : 3, "23-0" : 5, "23-1" : 2, "23-6" : 1, "23-4" : 2, "23-5" : 1, "0-5" : 2, "2-0" : 1, "0-0" : 1, "0-1" : 3, "0-2" : 2, "13-3" : 1, "13-0" : 3, "13-6" : 6, "13-5" : 2, "13-4" : 2, "20-1" : 5, "20-0" : 9, "20-3" : 4, "20-2" : 2, "20-5" : 7, "20-4" : 5, "20-6" : 1, "17-6" : 1, "17-5" : 3, "17-4" : 3, "17-3" : 4, "17-2" : 6, "17-1" : 12, "17-0" : 9, "10-2" : 1, "10-6" : 1, "0-6" : 3, "14-4" : 3, "14-5" : 2, "14-6" : 3, "14-0" : 3, "1-6" : 1 }, "_id" : { "$oid" : "5344d6d957d8c9771f7e6816" }, "type" : "checkin", "business_id" : "c5mGzf4ovtEglIzlXsL6rA" }, "full_address" : "2605 W Carefree Hwy\nPhoenix, AZ 85085", "hours" : { "Monday" : { "close" : "02:00", "open" : "11:00" }, "Tuesday" : { "close" : "02:00", "open" : "11:00" }, "Friday" : { "close" : "02:00", "open" : "11:00" }, "Wednesday" : { "close" : "02:00", "open" : "11:00" }, "Thursday" : { "close" : "02:00", "open" : "11:00" }, "Sunday" : { "close" : "02:00", "open" : "09:00" }, "Saturday" : { "close" : "02:00", "open" : "09:00" } }, "state" : "AZ", "longitude" : -112.1158534, "stars" : 3.5, "latitude" : 33.7978265, "attributes" : { "Drive-Thru" : false, "Alcohol" : "full_bar", "Noise Level" : "loud", "Music" : { "dj" : true, "background_music" : true, "karaoke" : true, "live" : false, "video" : true, "jukebox" : false }, "Attire" : "casual", "Ambience" : { "romantic" : false, "intimate" : false, "touristy" : false, "hipster" : false, "divey" : false, "classy" : false, "trendy" : false, "upscale" : false, "casual" : false }, "Good for Kids" : true, "Price Range" : 2, "Good For Dancing" : true, "Delivery" : false, "Coat Check" : false, "Smoking" : "outdoor", "Accepts Credit Cards" : true, "Take-out" : true, "Happy Hour" : true, "Wheelchair Accessible" : true, "Outdoor Seating" : true, "Takes Reservations" : true, "Waiter Service" : true, "Wi-Fi" : "free", "Good For" : { "dessert" : false, "latenight" : true, "lunch" : false, "dinner" : true, "breakfast" : false, "brunch" : false }, "Parking" : { "garage" : false, "street" : false, "validated" : false, "lot" : true, "valet" : false }, "Has TV" : true, "Good For Groups" : true }, "categories" : [ "Irish", "Bars", "Burgers", "Nightlife", "Sports Bars", "Restaurants" ], "votes" : [ { "funny" : 0, "useful" : 0, "cool" : 0 }, { "funny" : 0, "useful" : 0, "cool" : 0 }, { "funny" : 0, "useful" : 0, "cool" : 0 }, { "funny" : 0, "useful" : 1, "cool" : 0 }, { "funny" : 0, "useful" : 0, "cool" : 0 }, { "funny" : 0, "useful" : 0, "cool" : 0 }, { "funny" : 0, "useful" : 0, "cool" : 0 }, { "funny" : 0, "useful" : 1, "cool" : 0 }, { "funny" : 0, "useful" : 0, "cool" : 0 }, { "funny" : 0, "useful" : 0, "cool" : 0 }, { "funny" : 0, "useful" : 0, "cool" : 0 }, { "funny" : 0, "useful" : 0, "cool" : 0 }, { "funny" : 0, "useful" : 0, "cool" : 0 }, { "funny" : 0, "useful" : 0, "cool" : 0 }, { "funny" : 0, "useful" : 1, "cool" : 0 }, { "funny" : 0, "useful" : 0, "cool" : 0 }, { "funny" : 1, "useful" : 3, "cool" : 2 }, { "funny" : 3, "useful" : 3, "cool" : 4 }, { "funny" : 0, "useful" : 1, "cool" : 0 }, { "funny" : 0, "useful" : 0, "cool" : 0 }, { "funny" : 0, "useful" : 0, "cool" : 0 }, { "funny" : 8, "useful" : 7, "cool" : 6 }, { "funny" : 3, "useful" : 2, "cool" : 1 }, { "funny" : 0, "useful" : 0, "cool" : 0 }, { "funny" : 0, "useful" : 0, "cool" : 0 }, { "funny" : 0, "useful" : 1, "cool" : 0 }, { "funny" : 0, "useful" : 0, "cool" : 0 }, { "funny" : 3, "useful" : 2, "cool" : 0 }, { "funny" : 0, "useful" : 0, "cool" : 0 }, { "funny" : 0, "useful" : 1, "cool" : 0 }, { "funny" : 1, "useful" : 3, "cool" : 0 }, { "funny" : 0, "useful" : 0, "cool" : 0 }, { "funny" : 0, "useful" : 0, "cool" : 0 }, { "funny" : 0, "useful" : 0, "cool" : 0 }, { "funny" : 1, "useful" : 1, "cool" : 0 }, { "funny" : 0, "useful" : 0, "cool" : 0 }, { "funny" : 0, "useful" : 0, "cool" : 0 }, { "funny" : 2, "useful" : 1, "cool" : 1 }, { "funny" : 1, "useful" : 3, "cool" : 1 }, { "funny" : 0, "useful" : 0, "cool" : 0 } ], "open" : true },{ "_id" : { "$oid" : "5344d4cc57d8c9771f7d1050" }, "city" : "Phoenix", "neighborhood" : "Paradise Valley", "review_count" : 10, "name" : "Carte Blanche Gourmet Taco", "checkin" : { "checkin_info" : { "1-1" : 1, "15-0" : 1, "15-2" : 1, "13-1" : 1, "12-3" : 1, "8-1" : 1, "18-0" : 1, "16-3" : 2, "16-0" : 1, "18-6" : 1, "17-0" : 1, "10-0" : 1, "10-5" : 1 }, "_id" : { "$oid" : "5344d6d957d8c9771f7e5bad" }, "type" : "checkin", "business_id" : "dnhQaZ4wpLPwSfCleCILTg" }, "full_address" : "Phoenix, AZ 85032", "hours" : { "Monday" : { "close" : "00:00", "open" : "08:00" }, "Tuesday" : { "close" : "00:00", "open" : "08:00" }, "Friday" : { "close" : "00:00", "open" : "08:00" }, "Wednesday" : { "close" : "00:00", "open" : "08:00" }, "Thursday" : { "close" : "00:00", "open" : "08:00" }, "Saturday" : { "close" : "00:00", "open" : "08:00" } }, "state" : "AZ", "longitude" : -112.0118669, "stars" : 4, "latitude" : 33.6364503, "attributes" : { "Take-out" : true, "Accepts Credit Cards" : true, "Price Range" : 1, "Outdoor Seating" : false, "Caters" : true, "Attire" : "casual", "Good For Groups" : true, "Delivery" : false, "Dogs Allowed" : false, "Has TV" : false, "Good For" : { "dessert" : false, "latenight" : false, "lunch" : true, "dinner" : true, "breakfast" : false, "brunch" : false }, "Takes Reservations" : true, "Ambience" : { "romantic" : false, "intimate" : false, "classy" : false, "hipster" : false, "divey" : false, "touristy" : false, "trendy" : false, "casual" : true }, "Waiter Service" : true, "Wi-Fi" : "no", "Alcohol" : "none", "Wheelchair Accessible" : false }, "categories" : [ "Mexican", "Restaurants" ], "votes" : [ { "funny" : 1, "useful" : 2, "cool" : 2 }, { "funny" : 1, "useful" : 4, "cool" : 2 }, { "funny" : 1, "useful" : 2, "cool" : 1 }, { "funny" : 0, "useful" : 1, "cool" : 1 }, { "funny" : 0, "useful" : 0, "cool" : 0 }, { "funny" : 0, "useful" : 0, "cool" : 0 }, { "funny" : 0, "useful" : 0, "cool" : 0 }, { "funny" : 1, "useful" : 2, "cool" : 1 }, { "funny" : 0, "useful" : 0, "cool" : 0 } ], "open" : true },{ "_id" : { "$oid" : "5344d4cc57d8c9771f7d0a57" }, "city" : "Phoenix", "neighborhood" : "North Mountain", "review_count" : 42, "name" : "Grinders Coffee Company", "checkin" : { "checkin_info" : { "10-5" : 6, "8-6" : 4, "15-1" : 1, "15-0" : 2, "15-5" : 1, "18-1" : 2, "18-5" : 5, "12-0" : 1, "6-1" : 1, "14-2" : 2, "8-3" : 10, "16-4" : 2, "19-0" : 1, "11-5" : 3, "8-4" : 11, "13-6" : 1, "9-5" : 2, "12-4" : 1, "12-5" : 1, "6-2" : 1, "12-3" : 1, "6-0" : 1, "12-1" : 2, "9-0" : 4, "9-2" : 1, "4-4" : 1, "9-6" : 2, "7-3" : 2, "7-2" : 2, "7-1" : 5, "7-0" : 1, "20-5" : 2, "7-6" : 3, "7-5" : 1, "7-4" : 4, "16-2" : 1, "16-0" : 1, "17-3" : 2, "10-6" : 3, "17-1" : 1, "16-5" : 2, "10-0" : 1, "10-2" : 1, "10-3" : 3, "8-0" : 5, "8-1" : 3, "8-2" : 10, "11-0" : 2 }, "_id" : { "$oid" : "5344d6db57d8c9771f7e7f95" }, "type" : "checkin", "business_id" : "4eFIVmbeCvJGCrhzmd-VYA" }, "full_address" : "17 E Dunlap Ave\nSte 2\nPhoenix, AZ 85020", "hours" : { "Monday" : { "close" : "19:00", "open" : "06:00" }, "Tuesday" : { "close" : "19:00", "open" : "06:00" }, "Friday" : { "close" : "19:00", "open" : "06:00" }, "Wednesday" : { "close" : "19:00", "open" : "06:00" }, "Thursday" : { "close" : "19:00", "open" : "06:00" }, "Sunday" : { "close" : "14:00", "open" : "07:00" }, "Saturday" : { "close" : "16:00", "open" : "07:00" } }, "state" : "AZ", "longitude" : -112.0731019, "stars" : 4, "latitude" : 33.5675286, "attributes" : { "Wheelchair Accessible" : true, "Take-out" : true, "Accepts Credit Cards" : true, "Outdoor Seating" : true, "Noise Level" : "quiet", "Delivery" : false, "Has TV" : false, "Good For" : { "dessert" : false, "latenight" : false, "lunch" : false, "dinner" : false, "breakfast" : false, "brunch" : false }, "Parking" : { "garage" : false, "street" : false, "validated" : false, "lot" : true, "valet" : false }, "Ambience" : { "romantic" : false, "intimate" : false, "touristy" : false, "hipster" : false, "divey" : false, "classy" : false, "trendy" : false, "upscale" : false, "casual" : false }, "Wi-Fi" : "free", "Good for Kids" : false, "Alcohol" : "none", "Price Range" : 1 }, "categories" : [ "Food", "Coffee & Tea", "Sandwiches", "Restaurants" ], "votes" : [ { "funny" : 2, "useful" : 2, "cool" : 2 }, { "funny" : 0, "useful" : 1, "cool" : 1 }, { "funny" : 0, "useful" : 1, "cool" : 0 }, { "funny" : 1, "useful" : 1, "cool" : 0 }, { "funny" : 0, "useful" : 0, "cool" : 0 }, { "funny" : 1, "useful" : 2, "cool" : 1 }, { "funny" : 0, "useful" : 0, "cool" : 0 }, { "funny" : 3, "useful" : 4, "cool" : 4 }, { "funny" : 1, "useful" : 3, "cool" : 3 }, { "funny" : 1, "useful" : 2, "cool" : 2 }, { "funny" : 0, "useful" : 1, "cool" : 1 }, { "funny" : 0, "useful" : 1, "cool" : 0 }, { "funny" : 0, "useful" : 1, "cool" : 0 }, { "funny" : 0, "useful" : 2, "cool" : 3 }, { "funny" : 0, "useful" : 0, "cool" : 0 }, { "funny" : 1, "useful" : 1, "cool" : 1 }, { "funny" : 1, "useful" : 2, "cool" : 1 }, { "funny" : 1, "useful" : 4, "cool" : 1 }, { "funny" : 0, "useful" : 0, "cool" : 0 }, { "funny" : 0, "useful" : 0, "cool" : 0 }, { "funny" : 0, "useful" : 0, "cool" : 1 }, { "funny" : 0, "useful" : 0, "cool" : 0 }, { "funny" : 0, "useful" : 0, "cool" : 0 }, { "funny" : 0, "useful" : 1, "cool" : 0 }, { "funny" : 0, "useful" : 0, "cool" : 0 }, { "funny" : 1, "useful" : 3, "cool" : 1 }, { "funny" : 1, "useful" : 1, "cool" : 1 }, { "funny" : 0, "useful" : 0, "cool" : 0 }, { "funny" : 1, "useful" : 2, "cool" : 1 }, { "funny" : 0, "useful" : 0, "cool" : 0 }, { "funny" : 1, "useful" : 1, "cool" : 1 }, { "funny" : 0, "useful" : 0, "cool" : 0 }, { "funny" : 0, "useful" : 1, "cool" : 2 }, { "funny" : 0, "useful" : 0, "cool" : 0 }, { "funny" : 4, "useful" : 7, "cool" : 6 }, { "funny" : 0, "useful" : 0, "cool" : 1 }, { "funny" : 2, "useful" : 2, "cool" : 2 }, { "funny" : 1, "useful" : 1, "cool" : 1 }, { "funny" : 7, "useful" : 8, "cool" : 9 }, { "funny" : 1, "useful" : 2, "cool" : 2 } ], "open" : true },{ "_id" : { "$oid" : "5344d4cc57d8c9771f7d0aaf" }, "city" : "Phoenix", "neighborhood" : "Desert Ridge", "review_count" : 17, "name" : "Caf Allegro at MIM", "checkin" : { "checkin_info" : { "17-4" : 1, "15-5" : 1, "15-4" : 1, "18-3" : 1, "14-4" : 1, "14-5" : 1, "14-3" : 1, "11-5" : 1, "13-2" : 1, "13-1" : 1, "11-6" : 5, "10-0" : 2, "11-0" : 1, "13-5" : 3, "13-4" : 1, "12-6" : 1, "12-5" : 1, "12-2" : 1, "12-3" : 1, "9-0" : 1, "16-3" : 1, "16-0" : 1, "13-0" : 1, "8-4" : 2, "13-6" : 2 }, "_id" : { "$oid" : "5344d6da57d8c9771f7e79f6" }, "type" : "checkin", "business_id" : "T11YSYqwlRDC48V8-W1GRw" }, "full_address" : "4725 E Mayo Blvd\nPhoenix, AZ 85050", "hours" : { "Monday" : { "close" : "14:00", "open" : "11:00" }, "Tuesday" : { "close" : "14:00", "open" : "11:00" }, "Friday" : { "close" : "14:00", "open" : "11:00" }, "Wednesday" : { "close" : "14:00", "open" : "11:00" }, "Thursday" : { "close" : "14:00", "open" : "11:00" }, "Sunday" : { "close" : "14:00", "open" : "11:00" }, "Saturday" : { "close" : "14:00", "open" : "11:00" } }, "state" : "AZ", "longitude" : -111.9780526, "stars" : 3.5, "latitude" : 33.6676061, "attributes" : { "Take-out" : true, "Accepts Credit Cards" : true, "Price Range" : 2, "Outdoor Seating" : false, "Caters" : true, "Noise Level" : "quiet", "Parking" : { "garage" : false, "street" : false, "validated" : false, "lot" : true, "valet" : false }, "Good For Groups" : true, "Delivery" : false, "Dogs Allowed" : false, "Attire" : "casual", "Has TV" : false, "Good For" : { "dessert" : false, "latenight" : false, "lunch" : true, "dinner" : false, "breakfast" : false, "brunch" : false }, "Takes Reservations" : false, "Ambience" : { "romantic" : false, "intimate" : false, "touristy" : false, "hipster" : false, "divey" : false, "classy" : false, "trendy" : false, "upscale" : false, "casual" : false }, "Waiter Service" : false, "Wi-Fi" : "no", "Good for Kids" : true, "Alcohol" : "beer_and_wine", "Wheelchair Accessible" : true }, "categories" : [ "Food", "Desserts", "American (New)", "Pizza", "Restaurants" ], "votes" : [ { "funny" : 0, "useful" : 0, "cool" : 0 }, { "funny" : 8, "useful" : 13, "cool" : 10 }, { "funny" : 0, "useful" : 2, "cool" : 1 }, { "funny" : 1, "useful" : 1, "cool" : 0 }, { "funny" : 0, "useful" : 4, "cool" : 2 }, { "funny" : 1, "useful" : 0, "cool" : 0 }, { "funny" : 1, "useful" : 2, "cool" : 0 }, { "funny" : 1, "useful" : 3, "cool" : 1 }, { "funny" : 0, "useful" : 0, "cool" : 0 }, { "funny" : 0, "useful" : 4, "cool" : 1 }, { "funny" : 0, "useful" : 1, "cool" : 0 }, { "funny" : 0, "useful" : 0, "cool" : 0 }, { "funny" : 0, "useful" : 0, "cool" : 0 }, { "funny" : 0, "useful" : 3, "cool" : 0 }, { "funny" : 0, "useful" : 0, "cool" : 0 } ], "open" : true },{ "_id" : { "$oid" : "5344d4cc57d8c9771f7d0ad8" }, "city" : "Phoenix", "neighborhood" : "Camelback East", "review_count" : 11, "name" : "El Pollo Loco", "checkin" : { "checkin_info" : { "17-0" : 1, "13-4" : 1, "15-1" : 1, "15-0" : 1, "18-2" : 1, "15-6" : 2, "18-0" : 3, "18-1" : 2, "22-5" : 2, "18-3" : 2, "18-4" : 1, "18-5" : 1, "18-6" : 2, "23-5" : 1, "14-4" : 1, "14-5" : 2, "14-6" : 1, "14-1" : 1, "14-2" : 1, "14-3" : 1, "22-0" : 1, "19-1" : 1, "19-0" : 1, "19-2" : 4, "13-3" : 1, "11-6" : 1, "13-6" : 2, "13-5" : 1, "11-2" : 1, "12-6" : 2, "12-4" : 2, "12-2" : 3, "12-3" : 1, "12-1" : 2, "9-2" : 1, "20-5" : 3, "17-5" : 1, "13-0" : 1, "16-6" : 1, "16-5" : 2, "17-3" : 1, "10-2" : 1, "21-3" : 1, "10-4" : 1, "10-5" : 1, "10-6" : 1, "11-0" : 2 }, "_id" : { "$oid" : "5344d6d957d8c9771f7e6284" }, "type" : "checkin", "business_id" : "TBTaMIaeDw5B79hXDZBtrA" }, "full_address" : "4102 E Thomas Rd\nPhoenix, AZ 85018", "hours" : { "Monday" : { "close" : "22:00", "open" : "09:00" }, "Tuesday" : { "close" : "22:00", "open" : "09:00" }, "Friday" : { "close" : "23:00", "open" : "09:00" }, "Wednesday" : { "close" : "22:00", "open" : "09:00" }, "Thursday" : { "close" : "22:00", "open" : "09:00" }, "Sunday" : { "close" : "22:00", "open" : "09:00" }, "Saturday" : { "close" : "23:00", "open" : "09:00" } }, "state" : "AZ", "longitude" : -111.9926934, "stars" : 4, "latitude" : 33.4806911, "attributes" : { "Take-out" : true, "Price Range" : 1, "Outdoor Seating" : true, "Takes Reservations" : false, "Good For Groups" : true, "Delivery" : false, "Attire" : "casual", "Good For" : { "dessert" : false, "latenight" : false, "lunch" : false, "dinner" : false, "breakfast" : false, "brunch" : false }, "Parking" : { "garage" : false, "street" : false, "validated" : false, "lot" : false, "valet" : false }, "Ambience" : { "romantic" : false, "intimate" : false, "touristy" : false, "hipster" : false, "divey" : false, "classy" : false, "trendy" : false, "upscale" : false, "casual" : false }, "Waiter Service" : false, "Accepts Credit Cards" : true, "Good for Kids" : true, "Alcohol" : "none", "Wheelchair Accessible" : true }, "categories" : [ "Fast Food", "Mexican", "Restaurants" ], "votes" : [ { "funny" : 0, "useful" : 0, "cool" : 0 }, { "funny" : 0, "useful" : 1, "cool" : 1 }, { "funny" : 0, "useful" : 0, "cool" : 0 }, { "funny" : 0, "useful" : 0, "cool" : 0 }, { "funny" : 2, "useful" : 4, "cool" : 4 }, { "funny" : 0, "useful" : 0, "cool" : 0 }, { "funny" : 1, "useful" : 2, "cool" : 1 }, { "funny" : 0, "useful" : 1, "cool" : 0 } ], "open" : true },{ "_id" : { "$oid" : "5344d4cc57d8c9771f7d0c5a" }, "city" : "Phoenix", "neighborhood" : "Portland", "review_count" : 13, "name" : "Franks A Lot", "checkin" : { "checkin_info" : { "11-2" : 2, "15-4" : 1, "14-0" : 2, "19-3" : 1, "13-3" : 3, "13-2" : 3, "13-1" : 1, "13-0" : 1, "11-0" : 1, "13-4" : 3, "12-4" : 2, "12-2" : 1, "12-3" : 5, "12-0" : 1, "11-4" : 2, "17-6" : 1, "17-4" : 1, "10-0" : 1, "10-1" : 1, "10-2" : 1, "10-3" : 1, "10-4" : 1, "10-6" : 1 }, "_id" : { "$oid" : "5344d6d957d8c9771f7e6500" }, "type" : "checkin", "business_id" : "Qb0n61e_lsMmFuwwktjmjw" }, "full_address" : "15 N 40th St\nPhoenix, AZ 85034", "hours" : { "Thursday" : { "close" : "15:30", "open" : "09:30" }, "Tuesday" : { "close" : "15:30", "open" : "09:30" }, "Friday" : { "close" : "15:30", "open" : "09:30" }, "Wednesday" : { "close" : "15:30", "open" : "09:30" }, "Monday" : { "close" : "15:30", "open" : "09:30" } }, "state" : "AZ", "longitude" : -111.9953819, "stars" : 4, "latitude" : 33.4483495, "attributes" : { "Take-out" : true, "Accepts Credit Cards" : false, "Price Range" : 1, "Outdoor Seating" : true, "Caters" : false, "Noise Level" : "quiet", "Parking" : { "garage" : false, "street" : false, "validated" : false, "lot" : true, "valet" : false }, "Good For Groups" : true, "Delivery" : false, "Attire" : "casual", "Has TV" : false, "Good For" : { "dessert" : false, "latenight" : false, "lunch" : true, "dinner" : false, "breakfast" : false, "brunch" : false }, "Takes Reservations" : false, "Ambience" : { "romantic" : false, "intimate" : false, "touristy" : false, "hipster" : false, "divey" : false, "classy" : false, "trendy" : false, "upscale" : false, "casual" : true }, "Waiter Service" : false, "Wi-Fi" : "no", "Good for Kids" : true, "Alcohol" : "none", "Wheelchair Accessible" : true }, "categories" : [ "Burgers", "Hot Dogs", "Sandwiches", "Restaurants" ], "votes" : [ { "funny" : 0, "useful" : 0, "cool" : 0 }, { "funny" : 1, "useful" : 1, "cool" : 2 }, { "funny" : 12, "useful" : 21, "cool" : 21 }, { "funny" : 0, "useful" : 0, "cool" : 0 }, { "funny" : 0, "useful" : 0, "cool" : 0 }, { "funny" : 0, "useful" : 0, "cool" : 0 }, { "funny" : 0, "useful" : 0, "cool" : 0 }, { "funny" : 0, "useful" : 0, "cool" : 0 }, { "funny" : 0, "useful" : 0, "cool" : 0 }, { "funny" : 0, "useful" : 0, "cool" : 0 }, { "funny" : 10, "useful" : 11, "cool" : 9 }, { "funny" : 0, "useful" : 0, "cool" : 0 }, { "funny" : 9, "useful" : 10, "cool" : 9 }, { "funny" : 4, "useful" : 5, "cool" : 5 } ], "open" : true },{ "_id" : { "$oid" : "5344d4cc57d8c9771f7d0c99" }, "city" : "Phoenix", "neighborhood" : "Alhambra", "review_count" : 18, "name" : "Jersey Mike's", "checkin" : { "checkin_info" : { "17-0" : 1, "11-3" : 1, "11-2" : 5, "16-3" : 1, "15-5" : 2, "17-5" : 1, "15-6" : 2, "14-5" : 1, "14-6" : 1, "14-0" : 2, "14-2" : 1, "19-6" : 1, "19-1" : 2, "19-3" : 2, "19-2" : 1, "11-5" : 1, "13-2" : 3, "13-1" : 1, "11-6" : 1, "11-1" : 2, "11-0" : 4, "13-5" : 1, "13-4" : 1, "12-6" : 1, "12-4" : 2, "12-5" : 1, "12-2" : 1, "12-3" : 1, "12-0" : 4, "12-1" : 1, "11-4" : 2, "17-6" : 2, "16-0" : 1, "17-4" : 4, "17-2" : 2, "17-1" : 2, "16-5" : 1, "10-1" : 2, "10-3" : 2, "10-4" : 1 }, "_id" : { "$oid" : "5344d6da57d8c9771f7e7503" }, "type" : "checkin", "business_id" : "nRzZac3LVgANpKPkDs4LSQ" }, "full_address" : "18 East Camelback Road\nSte 18\nPhoenix, AZ 85012", "hours" : { "Monday" : { "close" : "21:00", "open" : "10:00" }, "Tuesday" : { "close" : "21:00", "open" : "10:00" }, "Friday" : { "close" : "21:00", "open" : "10:00" }, "Wednesday" : { "close" : "21:00", "open" : "10:00" }, "Thursday" : { "close" : "21:00", "open" : "10:00" }, "Sunday" : { "close" : "21:00", "open" : "10:00" }, "Saturday" : { "close" : "21:00", "open" : "10:00" } }, "state" : "AZ", "longitude" : -112.0730589, "stars" : 4, "latitude" : 33.509297, "attributes" : { "Take-out" : true, "Accepts Credit Cards" : true, "Drive-Thru" : false, "Outdoor Seating" : true, "Caters" : true, "Noise Level" : "average", "Parking" : { "garage" : false, "street" : false, "validated" : false, "lot" : true, "valet" : false }, "Delivery" : false, "Attire" : "casual", "Has TV" : false, "Price Range" : 1, "Good For" : { "dessert" : false, "latenight" : false, "lunch" : true, "dinner" : false, "breakfast" : false, "brunch" : false }, "Takes Reservations" : false, "Ambience" : { "romantic" : false, "intimate" : false, "touristy" : false, "hipster" : false, "divey" : false, "classy" : false, "trendy" : false, "upscale" : false, "casual" : true }, "Waiter Service" : false, "Wi-Fi" : "no", "Good for Kids" : true, "Good For Groups" : true, "Alcohol" : "none" }, "categories" : [ "Delis", "Fast Food", "Sandwiches", "Restaurants" ], "votes" : [ { "funny" : 0, "useful" : 0, "cool" : 0 }, { "funny" : 0, "useful" : 0, "cool" : 0 }, { "funny" : 1, "useful" : 1, "cool" : 0 }, { "funny" : 0, "useful" : 0, "cool" : 0 }, { "funny" : 1, "useful" : 3, "cool" : 1 }, { "funny" : 0, "useful" : 2, "cool" : 0 }, { "funny" : 0, "useful" : 2, "cool" : 0 }, { "funny" : 0, "useful" : 0, "cool" : 0 }, { "funny" : 0, "useful" : 0, "cool" : 0 }, { "funny" : 0, "useful" : 0, "cool" : 0 }, { "funny" : 0, "useful" : 0, "cool" : 0 }, { "funny" : 1, "useful" : 0, "cool" : 1 }, { "funny" : 0, "useful" : 0, "cool" : 0 }, { "funny" : 0, "useful" : 0, "cool" : 0 }, { "funny" : 0, "useful" : 0, "cool" : 0 }, { "funny" : 1, "useful" : 1, "cool" : 1 }, { "funny" : 0, "useful" : 1, "cool" : 1 }, { "funny" : 2, "useful" : 2, "cool" : 2 } ], "open" : true },{ "_id" : { "$oid" : "5344d4cc57d8c9771f7d0ceb" }, "city" : "Phoenix", "neighborhood" : "Desert Ridge", "review_count" : 30, "name" : "Slices", "checkin" : { "checkin_info" : { "13-4" : 1, "17-6" : 1, "15-0" : 1, "15-2" : 2, "15-4" : 1, "22-5" : 1, "18-3" : 1, "18-4" : 1, "21-5" : 1, "14-5" : 3, "17-5" : 1, "14-3" : 1, "16-4" : 1, "19-5" : 1, "19-4" : 1, "19-6" : 2, "19-1" : 1, "19-3" : 1, "11-4" : 1, "13-1" : 1, "11-6" : 1, "11-1" : 2, "11-0" : 1, "11-3" : 1, "11-2" : 1, "12-6" : 2, "12-4" : 2, "12-5" : 3, "12-2" : 2, "12-1" : 1, "20-3" : 1, "20-5" : 2, "16-2" : 1, "16-3" : 1, "16-0" : 1, "16-1" : 1, "16-6" : 1, "17-2" : 2, "17-1" : 2, "17-3" : 1 }, "_id" : { "$oid" : "5344d6da57d8c9771f7e7128" }, "type" : "checkin", "business_id" : "0ieEqGInYunNBaBzg8j_WQ" }, "full_address" : "21001 N Tatum Blvd\nPhoenix, AZ 85050", "hours" : { "Monday" : { "close" : "22:00", "open" : "11:00" }, "Tuesday" : { "close" : "22:00", "open" : "11:00" }, "Friday" : { "close" : "23:00", "open" : "11:00" }, "Wednesday" : { "close" : "22:00", "open" : "11:00" }, "Thursday" : { "close" : "22:00", "open" : "11:00" }, "Sunday" : { "close" : "20:00", "open" : "11:00" }, "Saturday" : { "close" : "23:00", "open" : "11:00" } }, "state" : "AZ", "longitude" : -111.9746066, "stars" : 3.5, "latitude" : 33.678615, "attributes" : { "Delivery" : false, "Take-out" : true, "Price Range" : 1, "Outdoor Seating" : true, "Good For Kids" : true, "Parking" : { "garage" : false, "street" : false, "validated" : false, "lot" : true, "valet" : false }, "Alcohol" : "none", "Good For Groups" : false, "BYOB" : false, "Attire" : "casual", "Corkage" : false, "Good For" : { "dessert" : false, "latenight" : false, "lunch" : true, "dinner" : true, "breakfast" : false, "brunch" : false }, "Takes Reservations" : false, "Ambience" : { "romantic" : false, "intimate" : false, "touristy" : false, "hipster" : false, "divey" : false, "classy" : false, "trendy" : false, "upscale" : false, "casual" : false }, "Waiter Service" : false, "Accepts Credit Cards" : true, "Good for Kids" : true, "BYOB/Corkage" : "yes_free", "Wheelchair Accessible" : true }, "categories" : [ "Pizza", "Restaurants" ], "votes" : [ { "funny" : 1, "useful" : 3, "cool" : 1 }, { "funny" : 1, "useful" : 2, "cool" : 1 }, { "funny" : 0, "useful" : 1, "cool" : 0 }, { "funny" : 0, "useful" : 2, "cool" : 0 }, { "funny" : 2, "useful" : 2, "cool" : 1 }, { "funny" : 0, "useful" : 0, "cool" : 0 }, { "funny" : 0, "useful" : 1, "cool" : 0 }, { "funny" : 0, "useful" : 0, "cool" : 0 }, { "funny" : 2, "useful" : 0, "cool" : 0 }, { "funny" : 0, "useful" : 0, "cool" : 0 }, { "funny" : 1, "useful" : 1, "cool" : 1 }, { "funny" : 0, "useful" : 0, "cool" : 1 }, { "funny" : 1, "useful" : 1, "cool" : 0 }, { "funny" : 0, "useful" : 0, "cool" : 0 }, { "funny" : 0, "useful" : 0, "cool" : 0 }, { "funny" : 0, "useful" : 0, "cool" : 0 }, { "funny" : 0, "useful" : 0, "cool" : 1 }, { "funny" : 0, "useful" : 0, "cool" : 0 }, { "funny" : 0, "useful" : 1, "cool" : 0 }, { "funny" : 0, "useful" : 0, "cool" : 0 }, { "funny" : 0, "useful" : 0, "cool" : 0 }, { "funny" : 1, "useful" : 3, "cool" : 3 }, { "funny" : 1, "useful" : 1, "cool" : 1 }, { "funny" : 0, "useful" : 1, "cool" : 0 }, { "funny" : 3, "useful" : 2, "cool" : 3 }, { "funny" : 2, "useful" : 2, "cool" : 1 }, { "funny" : 0, "useful" : 2, "cool" : 0 }, { "funny" : 0, "useful" : 0, "cool" : 0 }, { "funny" : 0, "useful" : 0, "cool" : 0 }, { "funny" : 0, "useful" : 0, "cool" : 0 } ], "open" : true },{ "_id" : { "$oid" : "5344d4cc57d8c9771f7d0d33" }, "city" : "Phoenix", "neighborhood" : "Encanto", "review_count" : 43, "name" : "The Phoenix Cheesesteak Co", "checkin" : { "checkin_info" : { "15-1" : 1, "15-3" : 1, "15-2" : 2, "15-5" : 1, "15-4" : 2, "14-4" : 2, "14-5" : 1, "14-0" : 1, "14-2" : 3, "14-3" : 1, "17-1" : 1, "13-3" : 3, "11-4" : 5, "13-0" : 2, "11-1" : 2, "11-0" : 6, "11-3" : 3, "11-2" : 5, "12-4" : 3, "12-5" : 2, "12-2" : 6, "12-3" : 7, "12-0" : 9, "12-1" : 7, "13-2" : 4, "16-2" : 3, "16-3" : 2, "16-0" : 2, "16-1" : 3, "17-3" : 2, "16-4" : 1, "16-5" : 1, "10-0" : 1, "10-1" : 1, "10-2" : 1, "10-3" : 1, "10-4" : 1, "10-5" : 3 }, "_id" : { "$oid" : "5344d6d857d8c9771f7e5a83" }, "type" : "checkin", "business_id" : "QwaoxP5Mgm3PJuZo_4bFsw" }, "full_address" : "2605 N 7th St\nPhoenix, AZ 85004", "hours" : { "Monday" : { "close" : "16:00", "open" : "09:00" }, "Tuesday" : { "close" : "16:00", "open" : "09:00" }, "Friday" : { "close" : "16:00", "open" : "09:00" }, "Wednesday" : { "close" : "16:00", "open" : "09:00" }, "Thursday" : { "close" : "16:00", "open" : "09:00" }, "Saturday" : { "close" : "18:00", "open" : "11:00" } }, "state" : "AZ", "longitude" : -112.064905, "stars" : 4.5, "latitude" : 33.4770071, "attributes" : { "Take-out" : true, "Accepts Credit Cards" : true, "Price Range" : 1, "Outdoor Seating" : false, "Caters" : true, "Noise Level" : "average", "Parking" : { "garage" : false, "street" : false, "validated" : false, "lot" : true, "valet" : false }, "Good For Groups" : true, "Delivery" : false, "Dogs Allowed" : false, "Attire" : "casual", "Has TV" : true, "Good For" : { "dessert" : false, "latenight" : false, "lunch" : true, "dinner" : false, "breakfast" : false, "brunch" : false }, "Takes Reservations" : false, "Ambience" : { "romantic" : false, "intimate" : false, "touristy" : false, "hipster" : false, "divey" : false, "classy" : false, "trendy" : false, "upscale" : false, "casual" : true }, "Waiter Service" : true, "Wi-Fi" : "no", "Good for Kids" : true, "Alcohol" : "none", "Wheelchair Accessible" : true }, "categories" : [ "Cheesesteaks", "Sandwiches", "Restaurants" ], "votes" : [ { "funny" : 0, "useful" : 2, "cool" : 2 }, { "funny" : 0, "useful" : 3, "cool" : 1 }, { "funny" : 0, "useful" : 4, "cool" : 1 }, { "funny" : 0, "useful" : 1, "cool" : 0 }, { "funny" : 1, "useful" : 2, "cool" : 0 }, { "funny" : 1, "useful" : 3, "cool" : 1 }, { "funny" : 0, "useful" : 0, "cool" : 1 }, { "funny" : 0, "useful" : 1, "cool" : 0 }, { "funny" : 3, "useful" : 2, "cool" : 2 }, { "funny" : 0, "useful" : 0, "cool" : 0 }, { "funny" : 0, "useful" : 1, "cool" : 1 }, { "funny" : 1, "useful" : 2, "cool" : 1 }, { "funny" : 0, "useful" : 2, "cool" : 1 }, { "funny" : 0, "useful" : 0, "cool" : 0 }, { "funny" : 0, "useful" : 2, "cool" : 0 }, { "funny" : 0, "useful" : 2, "cool" : 1 }, { "funny" : 0, "useful" : 0, "cool" : 2 }, { "funny" : 0, "useful" : 1, "cool" : 1 }, { "funny" : 2, "useful" : 3, "cool" : 2 }, { "funny" : 1, "useful" : 1, "cool" : 1 }, { "funny" : 0, "useful" : 0, "cool" : 0 }, { "funny" : 4, "useful" : 1, "cool" : 0 }, { "funny" : 0, "useful" : 0, "cool" : 0 }, { "funny" : 0, "useful" : 0, "cool" : 0 }, { "funny" : 0, "useful" : 0, "cool" : 0 }, { "funny" : 12, "useful" : 15, "cool" : 9 }, { "funny" : 1, "useful" : 3, "cool" : 2 }, { "funny" : 1, "useful" : 2, "cool" : 0 }, { "funny" : 0, "useful" : 0, "cool" : 0 }, { "funny" : 0, "useful" : 1, "cool" : 0 }, { "funny" : 0, "useful" : 4, "cool" : 1 }, { "funny" : 0, "useful" : 1, "cool" : 0 }, { "funny" : 0, "useful" : 0, "cool" : 0 }, { "funny" : 0, "useful" : 2, "cool" : 1 }, { "funny" : 0, "useful" : 0, "cool" : 0 }, { "funny" : 0, "useful" : 1, "cool" : 0 }, { "funny" : 0, "useful" : 0, "cool" : 0 }, { "funny" : 4, "useful" : 6, "cool" : 6 }, { "funny" : 1, "useful" : 4, "cool" : 1 }, { "funny" : 0, "useful" : 0, "cool" : 0 } ], "open" : false },{ "_id" : { "$oid" : "5344d4cc57d8c9771f7d0f7d" }, "city" : "Phoenix", "neighborhood" : "Paradise Gateway", "review_count" : 25, "name" : "Paradise Bakery", "checkin" : { "checkin_info" : { "13-6" : 2, "13-5" : 4, "11-2" : 6, "9-3" : 2, "10-1" : 1, "10-3" : 1, "15-0" : 1, "15-3" : 1, "15-5" : 1, "17-5" : 2, "15-6" : 1, "18-0" : 1, "18-2" : 2, "18-4" : 2, "18-5" : 2, "14-4" : 1, "14-5" : 3, "14-6" : 2, "14-0" : 2, "14-1" : 4, "14-2" : 2, "14-3" : 1, "9-0" : 1, "19-5" : 1, "16-5" : 1, "19-1" : 1, "19-0" : 2, "19-3" : 2, "13-3" : 2, "13-2" : 3, "13-1" : 3, "13-0" : 2, "11-1" : 4, "11-0" : 4, "11-3" : 1, "13-4" : 2, "12-4" : 4, "12-5" : 2, "12-2" : 5, "12-3" : 4, "12-0" : 5, "12-1" : 2, "11-5" : 2, "4-2" : 1, "9-2" : 4, "9-5" : 2, "8-0" : 3, "11-4" : 3, "20-1" : 1, "8-6" : 3, "7-5" : 1, "7-4" : 1, "16-2" : 2, "10-0" : 3, "16-0" : 2, "16-1" : 1, "10-6" : 5, "17-1" : 1, "17-0" : 3, "8-4" : 1, "8-5" : 2, "10-2" : 2, "21-3" : 1, "10-4" : 1, "10-5" : 3, "8-2" : 2, "8-3" : 1 }, "_id" : { "$oid" : "5344d6d957d8c9771f7e65c9" }, "type" : "checkin", "business_id" : "QxHM7gQ7RcRHjnmr63xQnQ" }, "full_address" : "10625 N. Tatum Blvd\nPhoenix, AZ 85028", "hours" : { "Monday" : { "close" : "21:00", "open" : "06:00" }, "Tuesday" : { "close" : "21:00", "open" : "06:00" }, "Friday" : { "close" : "21:00", "open" : "06:00" }, "Wednesday" : { "close" : "21:00", "open" : "06:00" }, "Thursday" : { "close" : "21:00", "open" : "06:00" }, "Sunday" : { "close" : "20:00", "open" : "06:00" }, "Saturday" : { "close" : "21:00", "open" : "06:00" } }, "state" : "AZ", "longitude" : -111.9768837, "stars" : 3, "latitude" : 33.5834251, "attributes" : { "Take-out" : true, "Accepts Credit Cards" : true, "Price Range" : 2, "Outdoor Seating" : true, "Caters" : true, "Noise Level" : "average", "Parking" : { "garage" : false, "street" : false, "validated" : false, "lot" : true, "valet" : false }, "Good For Groups" : true, "Delivery" : false, "Attire" : "casual", "Has TV" : false, "Good For" : { "dessert" : false, "latenight" : false, "lunch" : true, "dinner" : false, "breakfast" : false, "brunch" : false }, "Takes Reservations" : false, "Ambience" : { "romantic" : false, "intimate" : false, "touristy" : false, "hipster" : false, "divey" : false, "classy" : false, "trendy" : false, "upscale" : false, "casual" : true }, "Waiter Service" : false, "Wi-Fi" : "free", "Good for Kids" : true, "Alcohol" : "none", "Wheelchair Accessible" : true }, "categories" : [ "Bakeries", "Food", "Delis", "Sandwiches", "Restaurants" ], "votes" : [ { "funny" : 2, "useful" : 3, "cool" : 4 }, { "funny" : 0, "useful" : 1, "cool" : 0 }, { "funny" : 0, "useful" : 1, "cool" : 1 }, { "funny" : 0, "useful" : 0, "cool" : 0 }, { "funny" : 0, "useful" : 1, "cool" : 0 }, { "funny" : 0, "useful" : 1, "cool" : 0 }, { "funny" : 0, "useful" : 0, "cool" : 0 }, { "funny" : 0, "useful" : 0, "cool" : 0 }, { "funny" : 0, "useful" : 0, "cool" : 0 }, { "funny" : 0, "useful" : 1, "cool" : 1 }, { "funny" : 0, "useful" : 0, "cool" : 0 }, { "funny" : 0, "useful" : 0, "cool" : 0 }, { "funny" : 2, "useful" : 1, "cool" : 1 }, { "funny" : 0, "useful" : 2, "cool" : 0 }, { "funny" : 0, "useful" : 0, "cool" : 0 }, { "funny" : 1, "useful" : 2, "cool" : 1 }, { "funny" : 0, "useful" : 0, "cool" : 0 }, { "funny" : 0, "useful" : 1, "cool" : 0 }, { "funny" : 0, "useful" : 0, "cool" : 0 }, { "funny" : 0, "useful" : 0, "cool" : 0 }, { "funny" : 2, "useful" : 3, "cool" : 4 }, { "funny" : 0, "useful" : 0, "cool" : 0 }, { "funny" : 1, "useful" : 6, "cool" : 2 } ], "open" : true },{ "_id" : { "$oid" : "5344d4cc57d8c9771f7d1010" }, "city" : "Phoenix", "neighborhood" : "Medlock Place", "review_count" : 42, "name" : "Joyride Central", "checkin" : { "checkin_info" : { "17-0" : 1, "13-5" : 4, "17-6" : 2, "15-1" : 3, "10-4" : 2, "17-4" : 3, "15-2" : 1, "15-5" : 1, "15-4" : 1, "15-6" : 1, "18-0" : 2, "18-2" : 1, "18-3" : 2, "18-4" : 1, "18-5" : 1, "22-1" : 1, "21-5" : 2, "14-4" : 2, "14-5" : 2, "14-6" : 3, "18-6" : 2, "19-5" : 4, "19-4" : 3, "19-6" : 2, "19-1" : 2, "19-3" : 1, "19-2" : 2, "11-5" : 8, "13-2" : 1, "13-0" : 1, "11-1" : 2, "13-6" : 1, "11-3" : 1, "13-4" : 2, "12-6" : 4, "12-4" : 3, "12-5" : 8, "12-3" : 1, "12-0" : 1, "11-4" : 2, "20-0" : 2, "20-2" : 2, "20-5" : 2, "16-3" : 2, "17-5" : 4, "11-6" : 4, "16-6" : 1, "17-2" : 3, "17-1" : 2, "16-5" : 4, "21-4" : 1, "10-1" : 3, "10-2" : 2, "10-3" : 2, "21-0" : 1, "10-5" : 1, "10-6" : 1 }, "_id" : { "$oid" : "5344d6da57d8c9771f7e7cb8" }, "type" : "checkin", "business_id" : "1MQmujTuU-3qPdoogdA8CQ" }, "full_address" : "5202 N Central Ave\nPhoenix, AZ 85012", "hours" : { "Monday" : { "close" : "23:00", "open" : "11:00" }, "Tuesday" : { "close" : "23:00", "open" : "11:00" }, "Friday" : { "close" : "00:00", "open" : "11:00" }, "Wednesday" : { "close" : "23:00", "open" : "11:00" }, "Thursday" : { "close" : "23:00", "open" : "11:00" }, "Sunday" : { "close" : "22:00", "open" : "11:00" }, "Saturday" : { "close" : "00:00", "open" : "11:00" } }, "state" : "AZ", "longitude" : -112.073765, "stars" : 4, "latitude" : 33.51315, "attributes" : { "Take-out" : true, "Accepts Credit Cards" : true, "Price Range" : 2, "Outdoor Seating" : true, "Noise Level" : "average", "Attire" : "casual", "Delivery" : false, "Has TV" : true, "Good For" : { "dessert" : false, "latenight" : false, "lunch" : true, "dinner" : true, "breakfast" : false, "brunch" : false }, "Parking" : { "garage" : false, "street" : false, "validated" : false, "lot" : false, "valet" : true }, "Ambience" : { "romantic" : false, "intimate" : false, "classy" : false, "hipster" : false, "divey" : false, "touristy" : false, "trendy" : false, "upscale" : false, "casual" : false }, "Waiter Service" : true, "Wi-Fi" : "no", "Good for Kids" : true, "Good For Groups" : true, "Alcohol" : "full_bar" }, "categories" : [ "Mexican", "Restaurants" ], "votes" : [ { "funny" : 0, "useful" : 0, "cool" : 0 }, { "funny" : 0, "useful" : 1, "cool" : 0 }, { "funny" : 0, "useful" : 0, "cool" : 0 }, { "funny" : 0, "useful" : 0, "cool" : 0 }, { "funny" : 0, "useful" : 0, "cool" : 0 }, { "funny" : 0, "useful" : 1, "cool" : 0 }, { "funny" : 0, "useful" : 0, "cool" : 0 }, { "funny" : 0, "useful" : 2, "cool" : 1 }, { "funny" : 1, "useful" : 1, "cool" : 1 }, { "funny" : 0, "useful" : 0, "cool" : 0 }, { "funny" : 0, "useful" : 0, "cool" : 0 }, { "funny" : 0, "useful" : 0, "cool" : 0 }, { "funny" : 1, "useful" : 2, "cool" : 4 }, { "funny" : 0, "useful" : 1, "cool" : 2 }, { "funny" : 0, "useful" : 1, "cool" : 1 }, { "funny" : 0, "useful" : 0, "cool" : 0 }, { "funny" : 0, "useful" : 0, "cool" : 0 }, { "funny" : 1, "useful" : 4, "cool" : 4 }, { "funny" : 1, "useful" : 1, "cool" : 1 }, { "funny" : 0, "useful" : 0, "cool" : 0 }, { "funny" : 0, "useful" : 0, "cool" : 0 }, { "funny" : 0, "useful" : 0, "cool" : 0 }, { "funny" : 0, "useful" : 0, "cool" : 0 } ], "open" : true },{ "_id" : { "$oid" : "5344d4cc57d8c9771f7d10b1" }, "city" : "Phoenix", "neighborhood" : "Deer Valley Towne Square", "review_count" : 17, "name" : "Rubio's Fresh Mexican Grill", "checkin" : { "checkin_info" : { "13-5" : 1, "11-2" : 4, "15-1" : 2, "15-4" : 1, "18-0" : 1, "18-1" : 2, "16-1" : 3, "18-4" : 1, "14-6" : 1, "14-0" : 1, "14-2" : 1, "19-6" : 1, "19-1" : 2, "19-3" : 1, "19-2" : 1, "13-3" : 1, "11-4" : 1, "11-1" : 4, "11-3" : 1, "13-4" : 1, "12-6" : 2, "12-4" : 3, "12-2" : 3, "12-3" : 7, "12-0" : 5, "12-1" : 1, "11-5" : 1, "9-2" : 1, "10-4" : 1, "20-3" : 1, "20-2" : 2, "20-4" : 1, "16-2" : 2, "17-5" : 1, "17-4" : 1, "16-5" : 2, "10-0" : 1, "8-6" : 1, "10-3" : 3, "21-0" : 1, "10-6" : 1 }, "_id" : { "$oid" : "5344d6d957d8c9771f7e6038" }, "type" : "checkin", "business_id" : "FG7Js2aMD6NtMMRI0C8Arw" }, "full_address" : "3009 West Agua Fria Fwy.\nPhoenix, AZ 85027", "hours" : { "Monday" : { "close" : "21:00", "open" : "10:00" }, "Tuesday" : { "close" : "21:00", "open" : "10:00" }, "Friday" : { "close" : "22:00", "open" : "10:00" }, "Wednesday" : { "close" : "21:00", "open" : "10:00" }, "Thursday" : { "close" : "21:00", "open" : "10:00" }, "Sunday" : { "close" : "20:30", "open" : "11:00" }, "Saturday" : { "close" : "22:00", "open" : "10:00" } }, "state" : "AZ", "longitude" : -112.123307, "stars" : 3.5, "latitude" : 33.666702, "attributes" : { "Take-out" : true, "Price Range" : 2, "Outdoor Seating" : true, "Caters" : true, "Noise Level" : "average", "Parking" : { "garage" : false, "street" : false, "validated" : false, "lot" : false, "valet" : false }, "Good For Groups" : true, "Delivery" : false, "Attire" : "casual", "Has TV" : false, "Good For" : { "dessert" : false, "latenight" : false, "lunch" : true, "dinner" : true, "breakfast" : false, "brunch" : false }, "Takes Reservations" : false, "Ambience" : { "romantic" : false, "intimate" : false, "touristy" : false, "hipster" : false, "divey" : false, "classy" : false, "trendy" : false, "upscale" : false, "casual" : false }, "Waiter Service" : false, "Accepts Credit Cards" : true, "Good for Kids" : true, "Alcohol" : "beer_and_wine", "Wheelchair Accessible" : true }, "categories" : [ "Mexican", "Restaurants" ], "votes" : [ { "funny" : 0, "useful" : 0, "cool" : 0 }, { "funny" : 1, "useful" : 1, "cool" : 0 }, { "funny" : 0, "useful" : 1, "cool" : 0 }, { "funny" : 1, "useful" : 3, "cool" : 2 }, { "funny" : 2, "useful" : 4, "cool" : 3 }, { "funny" : 0, "useful" : 0, "cool" : 0 }, { "funny" : 0, "useful" : 0, "cool" : 0 }, { "funny" : 1, "useful" : 1, "cool" : 1 }, { "funny" : 0, "useful" : 0, "cool" : 0 }, { "funny" : 0, "useful" : 1, "cool" : 0 }, { "funny" : 0, "useful" : 0, "cool" : 0 }, { "funny" : 0, "useful" : 0, "cool" : 0 }, { "funny" : 0, "useful" : 0, "cool" : 0 }, { "funny" : 0, "useful" : 0, "cool" : 0 }, { "funny" : 0, "useful" : 0, "cool" : 0 }, { "funny" : 0, "useful" : 1, "cool" : 0 } ], "open" : false },{ "_id" : { "$oid" : "5344d4cc57d8c9771f7d1138" }, "city" : "Phoenix", "neighborhood" : "North Mountain", "review_count" : 15, "name" : "Native New Yorker", "checkin" : { "checkin_info" : { "16-0" : 1, "11-3" : 3, "11-2" : 3, "21-2" : 3, "15-1" : 1, "15-0" : 2, "22-5" : 1, "18-1" : 3, "18-2" : 1, "18-3" : 8, "18-4" : 3, "18-5" : 2, "23-4" : 1, "23-5" : 1, "14-6" : 3, "14-3" : 1, "18-6" : 4, "2-4" : 1, "19-5" : 1, "19-4" : 1, "19-6" : 2, "19-1" : 4, "19-0" : 1, "19-3" : 10, "19-2" : 1, "13-3" : 1, "11-4" : 3, "13-1" : 2, "17-0" : 1, "11-1" : 2, "13-5" : 2, "13-4" : 1, "12-6" : 2, "12-4" : 1, "12-2" : 5, "12-3" : 5, "12-1" : 4, "9-6" : 2, "20-1" : 1, "20-3" : 3, "20-5" : 3, "21-1" : 1, "16-3" : 2, "17-5" : 3, "17-4" : 1, "17-3" : 10, "17-2" : 2, "16-4" : 1, "16-5" : 1, "21-4" : 1, "22-2" : 1, "10-6" : 2, "21-3" : 1 }, "_id" : { "$oid" : "5344d6da57d8c9771f7e750f" }, "type" : "checkin", "business_id" : "QG4qmOPBgNigdI4cUYhKJg" }, "full_address" : "10004 N 26th Dr\nPhoenix, AZ 85021", "hours" : { "Monday" : { "close" : "00:00", "open" : "11:00" }, "Tuesday" : { "close" : "00:00", "open" : "11:00" }, "Friday" : { "close" : "01:00", "open" : "11:00" }, "Wednesday" : { "close" : "00:00", "open" : "11:00" }, "Thursday" : { "close" : "00:00", "open" : "11:00" }, "Sunday" : { "close" : "01:00", "open" : "11:00" }, "Saturday" : { "close" : "01:00", "open" : "11:00" } }, "state" : "AZ", "longitude" : -112.1161256, "stars" : 2.5, "latitude" : 33.5768931, "attributes" : { "Alcohol" : "full_bar", "Noise Level" : "average", "Music" : { "dj" : false, "background_music" : false, "jukebox" : false, "live" : false, "video" : false, "karaoke" : false }, "Attire" : "casual", "Ambience" : { "romantic" : false, "intimate" : false, "touristy" : false, "hipster" : false, "divey" : false, "classy" : false, "trendy" : false, "upscale" : false, "casual" : false }, "Price Range" : 2, "Good For Dancing" : false, "Delivery" : false, "Dogs Allowed" : false, "Coat Check" : false, "Smoking" : "no", "Accepts Credit Cards" : true, "Take-out" : true, "Happy Hour" : true, "Wheelchair Accessible" : true, "Outdoor Seating" : true, "Takes Reservations" : false, "Waiter Service" : true, "Wi-Fi" : "free", "Caters" : false, "Good For" : { "dessert" : false, "latenight" : false, "lunch" : false, "dinner" : false, "breakfast" : false, "brunch" : false }, "Parking" : { "garage" : false, "street" : false, "validated" : false, "lot" : true, "valet" : false }, "Has TV" : true, "Good For Groups" : true }, "categories" : [ "Nightlife", "Bars", "American (Traditional)", "Sports Bars", "Restaurants" ], "votes" : [ { "funny" : 0, "useful" : 1, "cool" : 1 }, { "funny" : 1, "useful" : 1, "cool" : 0 }, { "funny" : 0, "useful" : 1, "cool" : 0 }, { "funny" : 1, "useful" : 1, "cool" : 0 }, { "funny" : 0, "useful" : 0, "cool" : 0 }, { "funny" : 0, "useful" : 0, "cool" : 0 }, { "funny" : 0, "useful" : 0, "cool" : 0 }, { "funny" : 0, "useful" : 0, "cool" : 0 }, { "funny" : 0, "useful" : 0, "cool" : 0 }, { "funny" : 0, "useful" : 0, "cool" : 0 }, { "funny" : 0, "useful" : 0, "cool" : 0 }, { "funny" : 0, "useful" : 1, "cool" : 0 }, { "funny" : 0, "useful" : 1, "cool" : 0 }, { "funny" : 5, "useful" : 8, "cool" : 4 }, { "funny" : 0, "useful" : 0, "cool" : 0 } ], "open" : true }]
